{
  "date": "2026-07-24",
  "generated_at": "2026-07-24T18:12:16.125527+09:00",
  "window_hours": 30,
  "sources": [
    "네이버뉴스",
    "구글뉴스"
  ],
  "use_naver": true,
  "preview_items": 5,
  "counts": {
    "collected": 1882,
    "kept": 334,
    "excluded": 1548,
    "consolidated": 109,
    "multi": 41
  },
  "groups": [
    {
      "id": "gca",
      "label": "경기콘텐츠진흥원",
      "priority": 1,
      "count": 11,
      "items": [
        {
          "title": "[위클리오늘] 2026년 제2회 경기도 공공기관 통합채용…25개 기관 133명 ...",
          "url": "http://www.weeklytoday.com/news/articleView.html?idxno=787155",
          "snippet": "5명 ▲경기콘텐츠진흥원 3명 ▲경기대진테크노파크 2명 ▲경기도의료원 4명 ▲경기복지재단 2명 ▲경기도평생교육진흥원 4명 ▲경기도일자리재단 6명 ▲차세대융합기술연구원 3명 ▲경기도시장상권진흥원 4명...",
          "source": "weeklytoday.com",
          "sources": [
            {
              "name": "weeklytoday.com",
              "url": "http://www.weeklytoday.com/news/articleView.html?idxno=787155",
              "origin": "naver"
            },
            {
              "name": "breaknews.com",
              "url": "http://www.breaknews.com/1224243",
              "origin": "naver"
            },
            {
              "name": "suwonilbo.kr",
              "url": "http://www.suwonilbo.kr/news/articleView.html?idxno=316926",
              "origin": "naver"
            },
            {
              "name": "econonews.co.kr",
              "url": "http://www.econonews.co.kr/news/articleView.html?idxno=441716",
              "origin": "naver"
            }
          ],
          "source_count": 4,
          "published": "2026-07-24T16:46:00+09:00",
          "ts": 1784879160.0,
          "group": "gca",
          "group_label": "경기콘텐츠진흥원"
        },
        {
          "title": "[경기 24시] 경기도, 공공·유관기관 25곳 133명 통합채용 실시…필기시...",
          "url": "https://www.sisajournal.com/news/articleView.html?idxno=381031",
          "snippet": "5명 △경기콘텐츠진흥원 3명 △경기대진테크노파크 2명 △경기도의료원 4명 △경기복지재단 2명 △경기도평생교육진흥원 4명 △경기도일자리재단 6명 △차세대융합기술연구원 3명 △경기도시장상권진흥원 4명...",
          "source": "sisajournal.com",
          "sources": [
            {
              "name": "sisajournal.com",
              "url": "https://www.sisajournal.com/news/articleView.html?idxno=381076",
              "origin": "naver"
            },
            {
              "name": "YTN",
              "url": "https://www.ytn.co.kr/_ln/0115_202607241542478853",
              "origin": "naver"
            }
          ],
          "source_count": 2,
          "published": "2026-07-24T15:40:00+09:00",
          "ts": 1784875200.0,
          "group": "gca",
          "group_label": "경기콘텐츠진흥원"
        },
        {
          "title": "경기도, 25개 공공·유관기관 133명 선발",
          "url": "https://www.naeil.com/news/read/596459?ref=naver",
          "snippet": "5명 △경기콘텐츠진흥원 3명 △경기대진테크노파크 2명 △경기도의료원 4명 △경기복지재단 2명 △경기도평생교육진흥원 4명 △경기도일자리재단 6명 △차세대융합기술연구원 3명 △경기도시장상권진흥원 4명...",
          "source": "naeil.com",
          "sources": [
            {
              "name": "naeil.com",
              "url": "https://www.naeil.com/news/read/596459?ref=naver",
              "origin": "naver"
            },
            {
              "name": "sportsseoul.com",
              "url": "https://www.sportsseoul.com/news/read/1624408?ref=naver",
              "origin": "naver"
            }
          ],
          "source_count": 2,
          "published": "2026-07-24T11:00:00+09:00",
          "ts": 1784858400.0,
          "group": "gca",
          "group_label": "경기콘텐츠진흥원"
        },
        {
          "title": "경기도, 하반기 25개 공공기관서 133명 뽑는다",
          "url": "https://www.mk.co.kr/article/12106432",
          "snippet": "5명, 경기콘텐츠진흥원 3명, 경기대진테크노파크 2명, 경기도의료원 4명, 경기복지재단 2명, 경기도평생교육진흥원 4명, 경기도일자리재단 6명, 차세대융합기술연구원 3명, 경기도시장상권진흥원 4명...",
          "source": "매일경제",
          "sources": [
            {
              "name": "매일경제",
              "url": "https://www.mk.co.kr/article/12106432",
              "origin": "naver"
            },
            {
              "name": "머니투데이",
              "url": "https://www.mt.co.kr/policy/2026/07/24/2026072409131155488",
              "origin": "naver"
            }
          ],
          "source_count": 2,
          "published": "2026-07-24T10:36:00+09:00",
          "ts": 1784856960.0,
          "group": "gca",
          "group_label": "경기콘텐츠진흥원"
        },
        {
          "title": "올 하반기 경기도 공공기관 통합채 133명 선발… 9월5일 시험",
          "url": "https://www.m-i.kr/news/articleView.html?idxno=1395114",
          "snippet": "5명 △경기콘텐츠진흥원 3명 △경기대진테크노파크 2명 △경기도의료원 4명 △경기복지재단 2명 △경기도평생교육진흥원 4명 △경기도일자리재단 6명 △차세대융합기술연구원 3명 △경기도시장상권진흥원 4명...",
          "source": "m-i.kr",
          "sources": [
            {
              "name": "m-i.kr",
              "url": "https://www.m-i.kr/news/articleView.html?idxno=1395166",
              "origin": "naver"
            }
          ],
          "source_count": 1,
          "published": "2026-07-24T16:08:00+09:00",
          "ts": 1784876880.0,
          "group": "gca",
          "group_label": "경기콘텐츠진흥원"
        },
        {
          "title": "올해도 중국 시장 겨냥해 차이나조이로 향하는 한국 게임사들",
          "url": "https://game.donga.com/123523/",
          "snippet": "경기콘텐츠진흥원에서도 2026년 지커넥션 마켓 연계지원으로 모집한 10개 회사가 별도 공동관으로 참여한다. 모집 분야가 넓었던 만큼 대부분 콘텐츠, 캐릭터 기업이지만, 게임사인 뉴코어게임즈와 팀 테트라포드가...",
          "source": "동아일보",
          "sources": [
            {
              "name": "동아일보",
              "url": "https://game.donga.com/123523/",
              "origin": "naver"
            }
          ],
          "source_count": 1,
          "published": "2026-07-24T15:44:00+09:00",
          "ts": 1784875440.0,
          "group": "gca",
          "group_label": "경기콘텐츠진흥원"
        },
        {
          "title": "경기도, GH 50명 등 공공기관 133명 통합 채용",
          "url": "https://www.sedaily.com/article/20071398?ref=naver",
          "snippet": "5명 △경기콘텐츠진흥원 3명 △경기대진테크노파크 2명 △경기도의료원 4명 △경기복지재단 2명 △경기도평생교육진흥원 4명 △경기도일자리재단 6명 △차세대융합기술연구원 3명 △경기도시장상권진흥원 4명...",
          "source": "서울경제",
          "sources": [
            {
              "name": "서울경제",
              "url": "https://www.sedaily.com/article/20071398?ref=naver",
              "origin": "naver"
            }
          ],
          "source_count": 1,
          "published": "2026-07-24T10:20:00+09:00",
          "ts": 1784856000.0,
          "group": "gca",
          "group_label": "경기콘텐츠진흥원"
        },
        {
          "title": "GH 등 25개 공공기관 하반기 133명 채용한다…접수 8월10~14일",
          "url": "https://view.asiae.co.kr/article/2026072410111068532",
          "snippet": "5명 ▲경기콘텐츠진흥원 3명 ▲경기대진테크노파크 2명 ▲경기도의료원 4명 ▲경기복지재단 2명 ▲경기도평생교육진흥원 4명 ▲경기도일자리재단 6명 ▲차세대융합기술연구원 3명 ▲경기도시장상권진흥원 4명...",
          "source": "아시아경제",
          "sources": [
            {
              "name": "아시아경제",
              "url": "https://view.asiae.co.kr/article/2026072410111068532",
              "origin": "naver"
            }
          ],
          "source_count": 1,
          "published": "2026-07-24T10:11:00+09:00",
          "ts": 1784855460.0,
          "group": "gca",
          "group_label": "경기콘텐츠진흥원"
        },
        {
          "title": "경기도 공공기관 25곳 133명 채용…내달 10일부터 원서 접수",
          "url": "https://www.pressian.com/pages/articles/2026072409522339386?utm_source=naver&utm_medium=search",
          "snippet": "5명 △경기콘텐츠진흥원 3명 △경기대진테크노파크 2명 △경기도의료원 4명 △경기복지재단 2명 △경기도평생교육진흥원 4명 △경기도일자리재단 6명 △차세대융합기술연구원 3명 △경기도시장상권진흥원 4명...",
          "source": "프레시안",
          "sources": [
            {
              "name": "프레시안",
              "url": "https://www.pressian.com/pages/articles/2026072409522339386?utm_source=naver&utm_medium=search",
              "origin": "naver"
            }
          ],
          "source_count": 1,
          "published": "2026-07-24T09:54:00+09:00",
          "ts": 1784854440.0,
          "group": "gca",
          "group_label": "경기콘텐츠진흥원"
        },
        {
          "title": "투자 마중물 대폭 확대…경콘진, '2026 경기 레벨업 프로그램' 하반기 기업 모집",
          "url": "https://news.google.com/rss/articles/CBMiZEFVX3lxTFA2MWJMS3dLZ3p2RHlPWmJVWXNxS2VPdVc2VGVlc19POHhFOUhFUU4yWVNzNUhUdmRjWWwxc05QZXctam5BZGRITEQzVUEwQy1EV1dMcHZlM3RyYVlyQmoyUE56OHc?oc=5",
          "snippet": "",
          "source": "중앙뉴스타임스",
          "sources": [
            {
              "name": "중앙뉴스타임스",
              "url": "https://news.google.com/rss/articles/CBMiZEFVX3lxTFA2MWJMS3dLZ3p2RHlPWmJVWXNxS2VPdVc2VGVlc19POHhFOUhFUU4yWVNzNUhUdmRjWWwxc05QZXctam5BZGRITEQzVUEwQy1EV1dMcHZlM3RyYVlyQmoyUE56OHc?oc=5",
              "origin": "google"
            }
          ],
          "source_count": 1,
          "published": "2026-07-23T22:29:58+09:00",
          "ts": 1784813398.0,
          "group": "gca",
          "group_label": "경기콘텐츠진흥원"
        },
        {
          "title": "경기콘텐츠진흥원, '경기 레벨업 프로그램' 하반기 15개사 모집",
          "url": "https://platum.kr/archives/291311",
          "snippet": "경기콘텐츠진흥원(이하 경콘진)이 도내 콘텐츠·지식재산권(IP) 분야 스타트업을 대상으로 '2026 경기 레벨업 프로그램' 하반기 참여 기업을 모집한다. 접수는 지난 16일 시작해 8월 10일 오후 3시 마감한다. 선발 규모는...",
          "source": "platum.kr",
          "sources": [
            {
              "name": "platum.kr",
              "url": "https://platum.kr/archives/291311",
              "origin": "naver"
            }
          ],
          "source_count": 1,
          "published": "2026-07-23T13:26:00+09:00",
          "ts": 1784780760.0,
          "group": "gca",
          "group_label": "경기콘텐츠진흥원"
        }
      ]
    },
    {
      "id": "province",
      "label": "경기도(콘텐츠 관련)",
      "priority": 2,
      "count": 4,
      "items": [
        {
          "title": "파주시 운정다누림장애인복지관, 장애인 웹툰 창작소 '상상누림툰' 하반기 참여자 모집",
          "url": "https://news.google.com/rss/articles/CBMiakFVX3lxTE5GS3hrOVctVEdhbkJnbFlRR0EteG9IYk83NjltczI0Z0c2bWNaOVpTWDRhc1F3RFJvaFYwdTR2czgtQXM5RFlJMGp5cW1Cdkp6eVhfUVpiT2J6VjZnWmlUS01OZUpsYU45NGc?oc=5",
          "snippet": "",
          "source": "한국시사경제",
          "sources": [
            {
              "name": "한국시사경제",
              "url": "https://news.google.com/rss/articles/CBMiakFVX3lxTE5GS3hrOVctVEdhbkJnbFlRR0EteG9IYk83NjltczI0Z0c2bWNaOVpTWDRhc1F3RFJvaFYwdTR2czgtQXM5RFlJMGp5cW1Cdkp6eVhfUVpiT2J6VjZnWmlUS01OZUpsYU45NGc?oc=5",
              "origin": "google"
            },
            {
              "name": "중부시사신문",
              "url": "https://news.google.com/rss/articles/CBMiY0FVX3lxTFBLM011dWR4MFg3WTNuY3FWbFA0QnRpeTB3NGdxdWk3RmxHUm9heTUyeVhib2pBMGg4MmdOazJDSUVEd1NNajRkZEYtdE9KZUxoeEo3LVFqUlJhdGRZTHRtUU5QOA?oc=5",
              "origin": "google"
            }
          ],
          "source_count": 2,
          "published": "2026-07-24T14:31:36+09:00",
          "ts": 1784871096.0,
          "group": "province",
          "group_label": "경기도(콘텐츠 관련)"
        },
        {
          "title": "경기도 감사위 '2026 영화가 좋다! 청렴이 좋다!' 마련",
          "url": "https://www.newsclaim.co.kr/news/articleView.html?idxno=3070231",
          "snippet": "다양한 콘텐츠를 전시했습니다. 교육과 캠페인을 연계해 청렴 학습과 실천을 한 자리에서 이어갈 수 있도록 했습니다. 안상섭 경기도 감사위원회 위원장은 \"이번 행사는 강의식 교육에서 벗어나 공직자들이 일상 속에서...",
          "source": "newsclaim.co.kr",
          "sources": [
            {
              "name": "newsclaim.co.kr",
              "url": "https://www.newsclaim.co.kr/news/articleView.html?idxno=3070231",
              "origin": "naver"
            }
          ],
          "source_count": 1,
          "published": "2026-07-24T10:48:00+09:00",
          "ts": 1784857680.0,
          "group": "province",
          "group_label": "경기도(콘텐츠 관련)"
        },
        {
          "title": "경기도, 영화 속 사례로 청렴 배운다",
          "url": "https://www.naeil.com/news/read/596366?ref=naver",
          "snippet": "1층 로비에 청렴 포스터, 반부패 법령 안내 등 직원들이 청렴을 다지고 되새길 수 있는 다양한 콘텐츠를 전시했다. 안상섭 경기도 감사위원회 위원장은 “이번 행사는 강의식 교육에서 벗어나 공직자들이 일상 속에서...",
          "source": "naeil.com",
          "sources": [
            {
              "name": "naeil.com",
              "url": "https://www.naeil.com/news/read/596366?ref=naver",
              "origin": "naver"
            }
          ],
          "source_count": 1,
          "published": "2026-07-24T10:04:00+09:00",
          "ts": 1784855040.0,
          "group": "province",
          "group_label": "경기도(콘텐츠 관련)"
        },
        {
          "title": "[영상] 경기도·31개 시군, 민선 9기 첫 간담회…상생 협력 본격화",
          "url": "http://www.paxetv.com/news/articleView.html?idxno=277689",
          "snippet": "또한 반도체 산업이 집중된 지역과 그렇지 않은 지역 간 격차를 줄이고 특히 재정이 열악한 경기 북부에 대해서는 생활 인프라 확충 방안을 함께 마련하겠다고 강조했습니다. 이날 간담회에서는 각 시·군이 지역 현안과...",
          "source": "paxetv.com",
          "sources": [
            {
              "name": "paxetv.com",
              "url": "http://www.paxetv.com/news/articleView.html?idxno=277689",
              "origin": "naver"
            }
          ],
          "source_count": 1,
          "published": "2026-07-23T13:40:00+09:00",
          "ts": 1784781600.0,
          "group": "province",
          "group_label": "경기도(콘텐츠 관련)"
        }
      ]
    },
    {
      "id": "governor",
      "label": "경기도지사",
      "priority": 3,
      "count": 58,
      "items": [
        {
          "title": "추미애, 中 장쑤성장 취임축하 친서에 \"한중 지방정부 협력 모범 만들자...",
          "url": "https://www.etoday.co.kr/news/view/2607317",
          "snippet": "사례 추미애 경기도지사가 중국 장쑤성(江蘇省) 류샤오타오(刘小涛) 성장으로부터 취임 축하 친서를 받은 지... 24일 이투데이 취재를 종합하면, 추미애 지사는 '경기도-장쑤성 공동협의체' 제2차 회의 참석 후 귀국길에...",
          "source": "etoday.co.kr",
          "sources": [
            {
              "name": "etoday.co.kr",
              "url": "https://www.etoday.co.kr/news/view/2607317",
              "origin": "naver"
            },
            {
              "name": "뉴스핌",
              "url": "https://www.newspim.com/news/view/20260724001123",
              "origin": "naver"
            },
            {
              "name": "경기일보",
              "url": "https://www.kyeonggi.com/article/20260724580212",
              "origin": "naver"
            },
            {
              "name": "iminju.net",
              "url": "http://www.iminju.net/news/articleView.html?idxno=167114",
              "origin": "naver"
            },
            {
              "name": "아주경제",
              "url": "https://www.ajunews.com/view/20260724155914819",
              "origin": "naver"
            },
            {
              "name": "econonews.co.kr",
              "url": "http://www.econonews.co.kr/news/articleView.html?idxno=441766",
              "origin": "naver"
            },
            {
              "name": "뉴시스",
              "url": "https://www.newsis.com/view/NISX20260724_0003722468",
              "origin": "naver"
            },
            {
              "name": "디지털타임스",
              "url": "https://www.dt.co.kr/article/12074550?ref=naver",
              "origin": "naver"
            },
            {
              "name": "뉴스타운",
              "url": "https://news.google.com/rss/articles/CBMibkFVX3lxTE5GcUlMYVBkOHVXb2xZU3Q0c1lXQmJ6Vm1YWWFxcWE5SGJvdnptb0JyUjdlNXFrWUhKWTJ0c2dLTVlvMHRzRjdLWnl1M2tyczRMMHBLMzRFRTBXZTZXNjFfdjdJVGQxNk5ETmd0Qm1B?oc=5",
              "origin": "google"
            }
          ],
          "source_count": 9,
          "published": "2026-07-24T17:52:00+09:00",
          "ts": 1784883120.0,
          "group": "governor",
          "group_label": "경기도지사"
        },
        {
          "title": "\"성적 요구 거절 후 업무 배제\"…경기도청, 내부 폭로글 조사",
          "url": "http://mbn.mk.co.kr/pages/news/newsView.php?category=mbn00009&news_seq_no=5208049",
          "snippet": "이에 추미애 경기지사는 “최근 도청 내부에서 제기된 성 비위 사안과 관련해 무엇보다 피해자의 의사를 최우선으로 존중하여 신중하면서도 엄중하게 조치해달라”고 지시했습니다. 또 피해자 보호 및 2차 가해 철저 차단...",
          "source": "매일경제",
          "sources": [
            {
              "name": "매일경제",
              "url": "http://mbn.mk.co.kr/pages/news/newsView.php?category=mbn00009&news_seq_no=5208049",
              "origin": "naver"
            },
            {
              "name": "연합뉴스TV",
              "url": "http://www.yonhapnewstv.co.kr/news/AKR20260724163800NIQ",
              "origin": "naver"
            },
            {
              "name": "이데일리",
              "url": "https://www.edaily.co.kr/news/newspath.asp?newsid=04473926645517800",
              "origin": "naver"
            },
            {
              "name": "경향신문",
              "url": "https://www.khan.co.kr/article/202607241613001",
              "origin": "naver"
            },
            {
              "name": "bntnews.co.kr",
              "url": "https://www.bntnews.co.kr/article/view/bnt202607240221",
              "origin": "naver"
            },
            {
              "name": "헤럴드경제",
              "url": "https://biz.heraldcorp.com/article/10819450?ref=naver",
              "origin": "naver"
            },
            {
              "name": "파이낸셜뉴스",
              "url": "http://www.fnnews.com/news/202607241523592951",
              "origin": "naver"
            },
            {
              "name": "뉴스1",
              "url": "https://www.news1.kr/local/gyeonggi/6238153",
              "origin": "naver"
            }
          ],
          "source_count": 8,
          "published": "2026-07-24T17:30:00+09:00",
          "ts": 1784881800.0,
          "group": "governor",
          "group_label": "경기도지사"
        },
        {
          "title": "추미애 경기도지사, 박홍근 기획예산처 장관 만났다…\"경기남부광역철...",
          "url": "https://www.etoday.co.kr/news/view/2607315",
          "snippet": "문제제기 추미애 경기도지사가 정부 예산편성권을 쥔 박홍근 기획예산처 장관을 직접 만나 경기도 재정의... 24일 이투데이 취재를 종합하면 추미애 지사는 이날 정부서울청사에서 박홍근 기획예산처 장관을 만나 교통...",
          "source": "etoday.co.kr",
          "sources": [
            {
              "name": "etoday.co.kr",
              "url": "https://www.etoday.co.kr/news/view/2607315",
              "origin": "naver"
            },
            {
              "name": "newstnt.com",
              "url": "https://www.newstnt.com/news/articleView.html?idxno=711566",
              "origin": "naver"
            },
            {
              "name": "weeklytoday.com",
              "url": "http://www.weeklytoday.com/news/articleView.html?idxno=787167",
              "origin": "naver"
            },
            {
              "name": "hbnpress.com",
              "url": "https://hbnpress.com/news/view/1065597510252072",
              "origin": "naver"
            },
            {
              "name": "네이트",
              "url": "https://news.google.com/rss/articles/CBMiU0FVX3lxTFBxRVpENDhPUndDVnBBOTIyRTdzQi1nejdKQ0RjeGduTWpwNnZMM3g2U1hQb1NTejRNUVNiN0F4em5RTk1TU0ZCWVFPVmpSUnpOSExV?oc=5",
              "origin": "google"
            },
            {
              "name": "이투데이",
              "url": "https://news.google.com/rss/articles/CBMidEFVX3lxTFBweVp6ZmM3V2VBRU9neFp5X2RzOGZZcmpBOXpfT05ZV2dES0RZTmdYaVk3bFFlUlFDOFlpOFdOSFdWWGtfbXg5Nl96aU0wZnBVWFhGYl9TMU1vUWZWMEZEajJyNVlJQ0l2ZDRCbUJKNmVyeVo1?oc=5",
              "origin": "google"
            }
          ],
          "source_count": 6,
          "published": "2026-07-24T17:48:00+09:00",
          "ts": 1784882880.0,
          "group": "governor",
          "group_label": "경기도지사"
        },
        {
          "title": "추미애 경기도지사 \"재난 사각지대 없어야\"…주거취약 이주민 전수조사",
          "url": "https://news.google.com/rss/articles/CBMiakFVX3lxTE4xX1Frd3hheHRSZEtrVFVmUFVXZHZ5eXQzTS1ZSW0tbDI4ZV9BWU1iZnNKNkhwYW1mV0NqV2hoQ0RYV3R1b3FPZHlRaXItMUlLMnFabHpJN3haYnNIaUlrWWxrWmJfdDBuaXc?oc=5",
          "snippet": "",
          "source": "동양뉴스",
          "sources": [
            {
              "name": "동양뉴스",
              "url": "https://news.google.com/rss/articles/CBMiakFVX3lxTE4xX1Frd3hheHRSZEtrVFVmUFVXZHZ5eXQzTS1ZSW0tbDI4ZV9BWU1iZnNKNkhwYW1mV0NqV2hoQ0RYV3R1b3FPZHlRaXItMUlLMnFabHpJN3haYnNIaUlrWWxrWmJfdDBuaXc?oc=5",
              "origin": "google"
            },
            {
              "name": "아이뉴스24",
              "url": "https://news.google.com/rss/articles/CBMiTEFVX3lxTE1aRmNRd2xiVmZKYXdzZno3VXJGYXdYZnRnenphTVUzVGsyRm5OdUJTQjl2LTZaZDcyMThyNUhlZTVMdnNzem9iOW9fNUk?oc=5",
              "origin": "google"
            },
            {
              "name": "더팩트",
              "url": "https://news.google.com/rss/articles/CBMiVkFVX3lxTE1GOENDU2Q0d3p3RHFveVkyeEE1c0R2T3dsMzJJOU5HclgxUXd0VWhzMGJqbnpJWXdEM3Y3TGFUZDd3Rnh1Q0FhaERBQXp2cjhMMy1hMkpB0gFWQVVfeXFMTUY4Q0NTZDR3endEcW95WTJ4QTVzRHZPd2wzMkk5TkdyWDFRd3RVaHMwYmpueklZd0QzdjdMYVRkN3dGeHVDQWFoREFBenZyOEwzLWEySkE?oc=5",
              "origin": "google"
            },
            {
              "name": "아시아경제",
              "url": "https://news.google.com/rss/articles/CBMiYEFVX3lxTE83Q2pkNXYwcElmdy0ya2JSOEJjSGRuRnByTkxTNWZSeFFuTTRqVS16enNEdTFGMUV4c3I4WXR6ZmIwWjJDaFdJV1VMUmV3aGZQbmxtZ1gzelVXQ3lPZGtvaA?oc=5",
              "origin": "google"
            },
            {
              "name": "이코노뉴스",
              "url": "https://news.google.com/rss/articles/CBMib0FVX3lxTE94T2ZMX2NJN3ZQb08xb3BnLU56R0hIMTcyWk41SGhGMGt0SV9HMFBhSjh5WEdicTlsaDJwUXNEMkZOZVhhVEtBUFRacXRPME91c0FMUklwTzB0LUw3Skg1T2dJS1M0MWRod0ZkYngzWQ?oc=5",
              "origin": "google"
            }
          ],
          "source_count": 5,
          "published": "2026-07-24T11:56:00+09:00",
          "ts": 1784861760.0,
          "group": "governor",
          "group_label": "경기도지사"
        },
        {
          "title": "경기도청 성비위 폭로 파문…추미애 \"피해자보호·엄정 처분\"",
          "url": "https://www.sidae.com/article/2026072415364068156",
          "snippet": "추미애 경기도지사가 최근 경기도청 내부에서 성비위 의혹이 제기된 것과 관련해 피해자 보호와 가해자에 대한 엄정 처분을 지시했다. 24일 도에 따르면, 추 지사는 \"최근 도청 내부에서 제기된 성 비위 사안과 관련해...",
          "source": "sidae.com",
          "sources": [
            {
              "name": "sidae.com",
              "url": "https://www.sidae.com/article/2026072415364068156",
              "origin": "naver"
            },
            {
              "name": "중부일보",
              "url": "https://www.joongboo.com/news/articleView.html?idxno=363732274",
              "origin": "naver"
            },
            {
              "name": "이슈밸리",
              "url": "https://news.google.com/rss/articles/CBMibkFVX3lxTE4xaEhPeTJBNlFqNDlDdkdERk0yTHhOUklaMkhQNWtvbUY2UV9SejJFVXlTSnlMdjRLMkhlTm1XVmpzY0FIUzhnV1JqYmxqT1VJZXpQcWp5TmNHRkVONU9jNEppdndjdVVzR1JMLXFR?oc=5",
              "origin": "google"
            },
            {
              "name": "v.daum.net",
              "url": "https://news.google.com/rss/articles/CBMiT0FVX3lxTE96NnRpNElyb3hnajBTbmNhNk03RE9remxGc0ZUbEluaVYtc2JUUzBOSHl3aGRHYkI1Tm5IMm5OdUw5N0I2MkJZamk1VUlpamc?oc=5",
              "origin": "google"
            }
          ],
          "source_count": 4,
          "published": "2026-07-24T16:27:00+09:00",
          "ts": 1784878020.0,
          "group": "governor",
          "group_label": "경기도지사"
        },
        {
          "title": "장쑤성 대표단 방한…추미애 도지사 취임 축하·교류협력 강화",
          "url": "http://www.paxetv.com/news/articleView.html?idxno=277808",
          "snippet": "중국 장쑤성 대표단이 경기도를 찾아 추미애 경기도지사의 취임을 축하하는 친서를 전달했다/[사진=경기도] 중국 장쑤성 대표단이 경기도를 찾아 추미애 경기도지사의 취임을 축하하는 친서를 전달했습니다. 지난 23일...",
          "source": "paxetv.com",
          "sources": [
            {
              "name": "paxetv.com",
              "url": "http://www.paxetv.com/news/articleView.html?idxno=277808",
              "origin": "naver"
            },
            {
              "name": "팍스경제TV",
              "url": "https://news.google.com/rss/articles/CBMiZ0FVX3lxTFB1b0xHNk4yNjRjdFRkNThVbFlER0tERVN0Y0IteTc2ZkhqT05MTHhwOUMyU1NzV05LOTY0R1REUWRlQnF6SEdNOUJPT1QxV3JvcmxtOGRnUjA0M2NYazJVRW0tUnB0V2M?oc=5",
              "origin": "google"
            },
            {
              "name": "비즈월드",
              "url": "https://news.google.com/rss/articles/CBMia0FVX3lxTE03akVFZW1TSTNybXVXeHFyQUZzRjV0bGsyYUF2SW9RM1Fnbm5PYnJoTGRlc1V6eWl0WlFuMTRxT0hzb1BxYUpPamtwNjBWZ0Zab00za3lXVHYwMk9RT1EtQjdmS01fQ2FjbmhZ?oc=5",
              "origin": "google"
            },
            {
              "name": "파주에서신문",
              "url": "https://news.google.com/rss/articles/CBMiZ0FVX3lxTFBrMEtreHBjNUpZRlFrMDN6LWRiWGRSc3NwZHBPeTNMLXJQaXFtbHBUdjlyYUpBNUVRNE1fb091MFkxejBhcnU3NGdtWEk0MHUwb3REcmh0WmZhMHBkOTNoQ2dfMGluV1U?oc=5",
              "origin": "google"
            }
          ],
          "source_count": 4,
          "published": "2026-07-24T15:00:00+09:00",
          "ts": 1784872800.0,
          "group": "governor",
          "group_label": "경기도지사"
        },
        {
          "title": "추미애 경기도지사 \"경기미래투자공사 설립 속도 내라\"… 10월 초 시·군 협약 지시",
          "url": "https://news.google.com/rss/articles/CBMiZ0FVX3lxTFBRMTVIMzB2YmxOendiX1Z1UFpraXZEczNDVDdvSW5aanFvTlIyc0pvemVIMG9UblFLS01CRGRHaXFtZ1pjV3ZCT212UjNuNDM0NFZ4MnN4anozZWdPMDRPcGJJdUlER0U?oc=5",
          "snippet": "",
          "source": "경기도정신문",
          "sources": [
            {
              "name": "경기도정신문",
              "url": "https://news.google.com/rss/articles/CBMiZ0FVX3lxTFBRMTVIMzB2YmxOendiX1Z1UFpraXZEczNDVDdvSW5aanFvTlIyc0pvemVIMG9UblFLS01CRGRHaXFtZ1pjV3ZCT212UjNuNDM0NFZ4MnN4anozZWdPMDRPcGJJdUlER0U?oc=5",
              "origin": "google"
            },
            {
              "name": "서남투데이",
              "url": "https://news.google.com/rss/articles/CBMiWkFVX3lxTE9KQmx6NElWUW1DVXh5R19kVUxHLWl5c0ota3hfZEZialRYbFF0VHpuUVNUVDZGTUxVVDdzQ3pNajZabTVLOG8wLTRlQ2NINHpMaE1ZdFVWWEJNUQ?oc=5",
              "origin": "google"
            },
            {
              "name": "뉴스타운",
              "url": "https://news.google.com/rss/articles/CBMibkFVX3lxTE14bWJxUi1QWFg3MEhCZmRESTRadjBjYTFjdTBhQlRXQ1Nrejl4bnk1LXp4Y0ZxLTV3X0JNR1kxeEEtRFl4Tks3WWkzRWtuU29YYXV1dHR6aTF1aUxoamNQYjZhNVRJR1d4TWo0Snpn?oc=5",
              "origin": "google"
            },
            {
              "name": "경기신문",
              "url": "https://news.google.com/rss/articles/CBMiYkFVX3lxTE5PRG1yUk9JaGNkWENRTkRobnJyd2NLSV9WM1BrcGd3WGVxaVYxMERiN1h2OHhpM1dZdXZpNVRTY3RLbjdFci1xUzZPTFhFenk1S3plYUc5Mll5MWtwSG10RWd3?oc=5",
              "origin": "google"
            }
          ],
          "source_count": 4,
          "published": "2026-07-24T13:31:10+09:00",
          "ts": 1784867470.0,
          "group": "governor",
          "group_label": "경기도지사"
        },
        {
          "title": "추미애, 기획예산처 장관 만나 道사업 국비 지원 요청… 세제 개편 방안...",
          "url": "https://www.kyeongin.com/article/1767873",
          "snippet": "24일 정부서울청사서 박홍근 장관 면담 신규사업 규모 60조→100조 확대 건의 경기남부광역철도 반영 협조 요청하기도 道재정 문제 해결 위해 제도개선안 건의 추미애 경기도지사가 박홍근 기획예산처 장관을 만나...",
          "source": "kyeongin.com",
          "sources": [
            {
              "name": "kyeongin.com",
              "url": "https://www.kyeongin.com/article/1767873",
              "origin": "naver"
            },
            {
              "name": "경기일보",
              "url": "https://www.kyeonggi.com/article/20260724580222",
              "origin": "naver"
            },
            {
              "name": "news.ifm.kr",
              "url": "https://news.ifm.kr/news/articleView.html?idxno=475745",
              "origin": "naver"
            }
          ],
          "source_count": 3,
          "published": "2026-07-24T18:08:00+09:00",
          "ts": 1784884080.0,
          "group": "governor",
          "group_label": "경기도지사"
        },
        {
          "title": "‘낮엔 찜통, 밤엔 열대야’…경기도, 폭염 비상 1단계 가동",
          "url": "https://www.kyeonggi.com/article/20260724580238",
          "snippet": "아울러 추미애 경기도지사는 각 시·군과 관련 기관에 긴급 지시사항을 하달하며 철저한 현장 관리를... 추미애 지사는 “폭염은 도민의 생명을 위협하는 재난”이라며 “취약계층과 현장 근로자에게 피해가 발생하지...",
          "source": "경기일보",
          "sources": [
            {
              "name": "경기일보",
              "url": "https://www.kyeonggi.com/article/20260724580238",
              "origin": "naver"
            },
            {
              "name": "뉴시스",
              "url": "https://www.newsis.com/view/NISX20260724_0003722697",
              "origin": "naver"
            },
            {
              "name": "k-health.com",
              "url": "https://www.k-health.com/news/articleView.html?idxno=100274",
              "origin": "naver"
            }
          ],
          "source_count": 3,
          "published": "2026-07-24T18:04:00+09:00",
          "ts": 1784883840.0,
          "group": "governor",
          "group_label": "경기도지사"
        },
        {
          "title": "추미애 지사, 기획예산처 장관 면담...국비 4000억·지방재정 개혁 건의",
          "url": "https://www.newspim.com/news/view/20260724001131",
          "snippet": "추미애 경기도지사는 24일 정부서울청사에서 박홍근 기획예산처 장관을 만나 교통 인프라 확충 등... 추미애 경기도지사는 24일 정부서울청사에서 박홍근 기획예산처 장관을 만나 교통 인프라 확충 등 경기도의 5개...",
          "source": "뉴스핌",
          "sources": [
            {
              "name": "뉴스핌",
              "url": "https://www.newspim.com/news/view/20260724001131",
              "origin": "naver"
            },
            {
              "name": "beyondpost.co.kr",
              "url": "http://www.beyondpost.co.kr/view.php?ud=2026072416452038174c878f8fa1_30",
              "origin": "naver"
            },
            {
              "name": "sidae.com",
              "url": "https://www.sidae.com/article/2026072415565071813",
              "origin": "naver"
            }
          ],
          "source_count": 3,
          "published": "2026-07-24T17:38:00+09:00",
          "ts": 1784882280.0,
          "group": "governor",
          "group_label": "경기도지사"
        },
        {
          "title": "추미애 지사, 경기도 성비위 논란에 \"피해자 보호우선\"",
          "url": "http://www.hansbiz.co.kr/news/articleView.html?idxno=852322",
          "snippet": "추미애 경기도지사가 지난 10일 총괄과장급 실국장회의를 주재하고 있다. 추미애 경기도지사 페이스북 갈무리 | 수원=한스경제 김두일 기자 | 경기도청 내부 익명게시판에 직장 내 성비위와 보복성 업무 배제를 주장하는...",
          "source": "hansbiz.co.kr",
          "sources": [
            {
              "name": "hansbiz.co.kr",
              "url": "http://www.hansbiz.co.kr/news/articleView.html?idxno=852322",
              "origin": "naver"
            },
            {
              "name": "kyeongin.com",
              "url": "https://www.kyeongin.com/article/1767868",
              "origin": "naver"
            },
            {
              "name": "한스경제",
              "url": "https://news.google.com/rss/articles/CBMibEFVX3lxTFB0RjdMd05tQXZlbUp0Q1NsLVBISFdMM3IwbW9tUmFZcXNqanBNandTWVoxczR0dHNkRUdXSDNYYk5GZkNhNGczY0I4eGRuMS1TSEl0d2UzV1gyQThVc01qaEFfZmN3ejNlV3MwTQ?oc=5",
              "origin": "google"
            }
          ],
          "source_count": 3,
          "published": "2026-07-24T16:46:00+09:00",
          "ts": 1784879160.0,
          "group": "governor",
          "group_label": "경기도지사"
        },
        {
          "title": "추미애, 박홍근 장관에 \"경기도 재정 취약, 내년 국비 지원을\"",
          "url": "https://www.newsis.com/view/NISX20260724_0003722544",
          "snippet": "추미애 경기도지사가 24일 정부서울청사에서 박홍근 기획예산처 장관을 만나 경기도 현안을 설명하고 4000억원 규모의 내년도 국비 반영을 요청했다. 이번 면담은 기획예산처의 내년도 정부예산안 편성을 앞두고 주요...",
          "source": "뉴시스",
          "sources": [
            {
              "name": "뉴시스",
              "url": "https://www.newsis.com/view/NISX20260724_0003722544",
              "origin": "naver"
            },
            {
              "name": "오마이뉴스",
              "url": "https://www.ohmynews.com/NWS_Web/View/at_pg.aspx?CNTN_CD=A0003254000&CMPT_CD=P0010&utm_source=naver&utm_medium=newsearch&utm_campaign=naver_news",
              "origin": "naver"
            },
            {
              "name": "v.daum.net",
              "url": "https://news.google.com/rss/articles/CBMiT0FVX3lxTE5Ub0NhTnZxRkdBelJtWFlFc1NhZTJrclZJTDlvd1NJZE4wNnB5U0xjSkNYdlpHQ1A1cmRZZXRMUVpwZkptdVhCcXdqdU9ieGc?oc=5",
              "origin": "google"
            }
          ],
          "source_count": 3,
          "published": "2026-07-24T16:34:00+09:00",
          "ts": 1784878440.0,
          "group": "governor",
          "group_label": "경기도지사"
        },
        {
          "title": "추미애 \"찜통 비닐하우스 없어져야\"…경기도, 이주노동자 주거환경 대수...",
          "url": "https://www.asiatoday.co.kr/kn/view.php?key=20260724010008968",
          "snippet": "다음 달 14일까지 주거취약시설 4400여곳 전수 점검 도청내 성비위 의혹에 \"독립적 조사, 엄중조치하라\" 지시 추미애 경기도지사는 \"기후재난에 가까운 폭염은 주거 기반이 약한 이들에게 생존의 문제로 직결된다\"면서 \"재난...",
          "source": "asiatoday.co.kr",
          "sources": [
            {
              "name": "asiatoday.co.kr",
              "url": "https://www.asiatoday.co.kr/kn/view.php?key=20260724010008968",
              "origin": "naver"
            },
            {
              "name": "네이트",
              "url": "https://news.google.com/rss/articles/CBMiU0FVX3lxTE1GTXpVU3lYRmtHRFloNjNNMUVlZlZsR0NET25NWUdKeUo2MWFQQkNud2h3MG05OGIyYzlWZ2hZckpDc1VWRHVLNDdzaHBvMGV3eHpJ?oc=5",
              "origin": "google"
            },
            {
              "name": "아시아투데이",
              "url": "https://news.google.com/rss/articles/CBMibkFVX3lxTE1TNzg2dEVHdmxaY1g0dk9TSXZxczY3ajYwcVk5MHF2RHhfbFhQb3hHaGNPNUFfTy1RRzZkUmh3Qms0QW5xWlpYakVLemZoVmVPSFNxUWJpZnpEajRqWnpnX2h3ZXdRLXR4TTNwYnJ3?oc=5",
              "origin": "google"
            }
          ],
          "source_count": 3,
          "published": "2026-07-24T15:06:00+09:00",
          "ts": 1784873160.0,
          "group": "governor",
          "group_label": "경기도지사"
        },
        {
          "title": "추미애, 경기남부광역철도 국가계획 반영 요청…교통·복지 국비 확보 ...",
          "url": "http://www.babytimes.co.kr/news/articleView.html?idxno=73648",
          "snippet": "추미애 경기도지사가 24일 박홍근 기획예산처 장관에게 경기남부광역철도 등 경기도 건의사업의 제5차... (사진=경기도청 제공) 추미애 경기도지사가 경기남부광역철도의 국가계획 반영과 광역버스·특별교통수단 등...",
          "source": "babytimes.co.kr",
          "sources": [
            {
              "name": "babytimes.co.kr",
              "url": "http://www.babytimes.co.kr/news/articleView.html?idxno=73648",
              "origin": "naver"
            },
            {
              "name": "consumernews.co.kr",
              "url": "http://www.consumernews.co.kr/news/articleView.html?idxno=760038",
              "origin": "naver"
            }
          ],
          "source_count": 2,
          "published": "2026-07-24T17:50:00+09:00",
          "ts": 1784883000.0,
          "group": "governor",
          "group_label": "경기도지사"
        },
        {
          "title": "추미애, 박홍근 만나 재정 지원 총력전…4000억 원 국비·경기남부광역...",
          "url": "https://news.tf.co.kr/read/national/2346918.htm",
          "snippet": "추미애 경기도지사가 24일 정부에 지방재정 제도개선과 함께 4000억 원 규모의 국비 지원을 요청하며 재정 확보전에 나섰다. 특히 경기남부광역철도의 국가철도망 반영과 광역버스 준공영제 등 핵심 현안의 정부...",
          "source": "news.tf.co.kr",
          "sources": [
            {
              "name": "news.tf.co.kr",
              "url": "https://news.tf.co.kr/read/national/2346918.htm",
              "origin": "naver"
            },
            {
              "name": "아주경제",
              "url": "https://www.ajunews.com/view/20260724160800829",
              "origin": "naver"
            }
          ],
          "source_count": 2,
          "published": "2026-07-24T17:38:00+09:00",
          "ts": 1784882280.0,
          "group": "governor",
          "group_label": "경기도지사"
        },
        {
          "title": "[오늘의 행정 일기]추미애 경기지사, 中 장쑤성장과 친서 교환 “한중 ...",
          "url": "https://www.nspna.com/news/?mode=view&newsid=821908",
          "snippet": "기대 추미애 경기도지사가 대한민국 최대 교역 파트너이자 중국 경제의 핵심 거점인 장쑤성(江蘇省)의... 24일 경기도에 따르면 추미애 지사는 이날 귀국길에 오르는 장쑤성 대표단을 통해 류샤오타오 성장에게 전하는...",
          "source": "nspna.com",
          "sources": [
            {
              "name": "nspna.com",
              "url": "https://www.nspna.com/news/?mode=view&newsid=821908",
              "origin": "naver"
            },
            {
              "name": "weeklytoday.com",
              "url": "http://www.weeklytoday.com/news/articleView.html?idxno=787165",
              "origin": "naver"
            }
          ],
          "source_count": 2,
          "published": "2026-07-24T17:38:00+09:00",
          "ts": 1784882280.0,
          "group": "governor",
          "group_label": "경기도지사"
        },
        {
          "title": "추미애 지사 기재부 찾아 철도망·교통 예산 등 4천억 지원 요청",
          "url": "https://www.obsnews.co.kr/news/articleView.html?idxno=1531756",
          "snippet": "추미애 경기도지사가 정부를 찾아 재정 어려움을 설명하며 제도 개선과 내년도 주요 사업에 대한 국비 지원을 요청했습니다. 추 지사는 정부서울청사에서 박홍근 기획예산처 장관을 만나 교통 인프라 확충 등 5개 주요...",
          "source": "obsnews.co.kr",
          "sources": [
            {
              "name": "obsnews.co.kr",
              "url": "https://www.obsnews.co.kr/news/articleView.html?idxno=1531756",
              "origin": "naver"
            },
            {
              "name": "중부일보",
              "url": "https://www.joongboo.com/news/articleView.html?idxno=363732277",
              "origin": "naver"
            }
          ],
          "source_count": 2,
          "published": "2026-07-24T17:14:00+09:00",
          "ts": 1784880840.0,
          "group": "governor",
          "group_label": "경기도지사"
        },
        {
          "title": "경기도, 민선 9기 초대 경제부지사 주형철 내정",
          "url": "https://www.dt.co.kr/article/12074543?ref=naver",
          "snippet": "추미애 경기도지사는 주형철 경제부지사 내정에 대해 “대한민국의 혁신 경제성장을 위해서는 경기도의 선도적인 역할이 무엇보다 중요하다.”고 강조하며, “경기도의 첨단산업 발전과 민생 경제 활성화를 위해 주요...",
          "source": "디지털타임스",
          "sources": [
            {
              "name": "디지털타임스",
              "url": "https://www.dt.co.kr/article/12074543?ref=naver",
              "origin": "naver"
            },
            {
              "name": "천지일보",
              "url": "https://news.google.com/rss/articles/CBMiakFVX3lxTE9FSFFORW00eFZlTEQ0cTdaNndsaTJqVk5aMjlPb1k0WXNpNjY3TjVkcDRVNVluNzhETlh5TVdlaHlGUVNSbTY5ZjhBVGRXZERwVDhVbVNSSnU5c2J2aGZoWUtnNUd5QmozSVE?oc=5",
              "origin": "google"
            }
          ],
          "source_count": 2,
          "published": "2026-07-24T15:13:00+09:00",
          "ts": 1784873580.0,
          "group": "governor",
          "group_label": "경기도지사"
        },
        {
          "title": "추미애 경기도지사 \"반도체 슈퍼사이클에도 경기도는 10원도 못 만져\"…도민 참여 펀드 승부수",
          "url": "https://news.google.com/rss/articles/CBMieEFVX3lxTE9ibHBjQVlXSXR2anY3bm55b2FyLUw4aXR3MnBoSXRQNk1rcDlSZXJoRko4LXY1Z0hseVZubndsSFFXSTBsNjZ4XzBhaXBmLXZCN2FYQ2o0UTIwOEFVVUVZbm5tQUFQanhuNDlmRy1OVU1Ja194ZlhOYg?oc=5",
          "snippet": "",
          "source": "네이트",
          "sources": [
            {
              "name": "네이트",
              "url": "https://news.google.com/rss/articles/CBMieEFVX3lxTE9ibHBjQVlXSXR2anY3bm55b2FyLUw4aXR3MnBoSXRQNk1rcDlSZXJoRko4LXY1Z0hseVZubndsSFFXSTBsNjZ4XzBhaXBmLXZCN2FYQ2o0UTIwOEFVVUVZbm5tQUFQanhuNDlmRy1OVU1Ja194ZlhOYg?oc=5",
              "origin": "google"
            },
            {
              "name": "뉴시스",
              "url": "https://news.google.com/rss/articles/CBMieEFVX3lxTE1xM2FuQU5SM3M0RkpubkFuOUVQcy1wSE5HbkltREJTeEJwdFhhVXdKWXZIVFVlcHQ3U213X1ZyUW9tcVhWcF9zZXZKN0piVlpsMnhVUTZvX2ExekdwVDQxblRCM0ppX0NhckpYeEtUM3RSMnVvamRwUdIBeEFVX3lxTE1xM2FuQU5SM3M0RkpubkFuOUVQcy1wSE5HbkltREJTeEJwdFhhVXdKWXZIVFVlcHQ3U213X1ZyUW9tcVhWcF9zZXZKN0piVlpsMnhVUTZvX2ExekdwVDQxblRCM0ppX0NhckpYeEtUM3RSMnVvamRwUQ?oc=5",
              "origin": "google"
            }
          ],
          "source_count": 2,
          "published": "2026-07-24T14:12:00+09:00",
          "ts": 1784869920.0,
          "group": "governor",
          "group_label": "경기도지사"
        },
        {
          "title": "추미애, 도청 성비위 의혹 ‘직보체계’ 가동…“피해자 의사 최우선”",
          "url": "https://www.etoday.co.kr/news/view/2607319",
          "snippet": "이투데이=경기인천취재본부 김재학 기자 | 내부게시판에 성적 요구 거절 뒤 업무배제 주장…2차 가해 차단·독립 조사·엄정 처분 지시 추미애 경기도지사가 도청 내부에서 제기된 성비위와 보복성 업무배제 의혹을 도지사...",
          "source": "etoday.co.kr",
          "sources": [
            {
              "name": "etoday.co.kr",
              "url": "https://www.etoday.co.kr/news/view/2607319",
              "origin": "naver"
            }
          ],
          "source_count": 1,
          "published": "2026-07-24T18:00:00+09:00",
          "ts": 1784883600.0,
          "group": "governor",
          "group_label": "경기도지사"
        },
        {
          "title": "경기도, 폭염 특보 확대에 재난안전대책본부 1단계 가동",
          "url": "https://www.newspim.com/news/view/20260724001158",
          "snippet": "이와 함께 추미애 경기도지사는 각 시·군 및 관계 부서에 긴급 지시사항을 하달하며 대비태세를 강화할... 추미애 경기도지사는 \"폭염은 도민의 생명과 안전을 직접적으로 위협하는 재난\"이라며 \"취약계층과 현장...",
          "source": "뉴스핌",
          "sources": [
            {
              "name": "뉴스핌",
              "url": "https://www.newspim.com/news/view/20260724001158",
              "origin": "naver"
            }
          ],
          "source_count": 1,
          "published": "2026-07-24T17:52:00+09:00",
          "ts": 1784883120.0,
          "group": "governor",
          "group_label": "경기도지사"
        },
        {
          "title": "경기도, 광역버스·특별교통수단 국비 지원 요청…교통 이동권 강화",
          "url": "https://www.safetynews.co.kr/news/articleView.html?idxno=249736",
          "snippet": "추미애 경기도지사가 24일 박홍근 기획예산처 장관과 광역버스 준공영제, 특별교통수단 운영, 친환경 2층... 추미애 경기도지사는 24일 박홍근 기획예산처 장관을 만나 2027년도 정부예산안에 경기도 주요 사업을 반영해...",
          "source": "safetynews.co.kr",
          "sources": [
            {
              "name": "safetynews.co.kr",
              "url": "https://www.safetynews.co.kr/news/articleView.html?idxno=249736",
              "origin": "naver"
            }
          ],
          "source_count": 1,
          "published": "2026-07-24T17:36:00+09:00",
          "ts": 1784882160.0,
          "group": "governor",
          "group_label": "경기도지사"
        },
        {
          "title": "추미애 지사, 정부에 4000억원 규모 내년 국비 사업 반영 요청",
          "url": "https://www.kukinews.com/article/view/kuk202607240149",
          "snippet": "추미애 경기도지사가 24일 정부서울청사에서 박홍근 기획예산처 장관을 만나 4000억원 규모 내년 국비 사업의 반영을 요청했다. 이와 함께 지방재정의 안정성과 재정분권 강화를 위한 제도개선을 건의했다. 이번 면담은...",
          "source": "쿠키뉴스",
          "sources": [
            {
              "name": "쿠키뉴스",
              "url": "https://www.kukinews.com/article/view/kuk202607240149",
              "origin": "naver"
            }
          ],
          "source_count": 1,
          "published": "2026-07-24T17:30:00+09:00",
          "ts": 1784881800.0,
          "group": "governor",
          "group_label": "경기도지사"
        },
        {
          "title": "성 비위 폭로 글에 경기도청 '발칵'…추미애 지사 엄중조치 지시·특별...",
          "url": "https://www.ngonews.kr/news/articleView.html?idxno=233741",
          "snippet": "경기도는 해당 의혹에 대한 사실관계 확인에 착수했으며, 추미애 경기도지사는 피해자 보호와 엄정한 조치를... 경기도 조사 착수…추미애 지사 특별 지시 논란이 커지자 경기도는 즉시 사실관계 확인 절차에 들어갔다. 도...",
          "source": "ngonews.kr",
          "sources": [
            {
              "name": "ngonews.kr",
              "url": "https://www.ngonews.kr/news/articleView.html?idxno=233741",
              "origin": "naver"
            }
          ],
          "source_count": 1,
          "published": "2026-07-24T17:14:00+09:00",
          "ts": 1784880840.0,
          "group": "governor",
          "group_label": "경기도지사"
        },
        {
          "title": "추미애 지사, 도청 내 성비위에 ‘무관용 엄중조치’ 지시",
          "url": "https://www.kgnews.co.kr/news/article.html?no=905082",
          "snippet": "추미애 경기도지사는 24일 경기도청 도내 익명 소통 게시판인 ‘와글와글’에 직장 내 성비위와 2차 가해를 주장하는 글이 게재된 것과 관련해 피재하 의사를 존중해 신중하고 엄중한 조치에 나설 것을 지시했다. 추미애...",
          "source": "경기신문",
          "sources": [
            {
              "name": "경기신문",
              "url": "https://www.kgnews.co.kr/news/article.html?no=905082",
              "origin": "naver"
            }
          ],
          "source_count": 1,
          "published": "2026-07-24T17:12:00+09:00",
          "ts": 1784880720.0,
          "group": "governor",
          "group_label": "경기도지사"
        },
        {
          "title": "추미애 지사, 박홍근 장관 만나 4000억 원 국비 요청...경기도 재정구조 한계",
          "url": "https://news.google.com/rss/articles/CBMiWkFVX3lxTFBtay1YWjZiTUNJV0RYRFRVeTlOVDNuVlRWaXVyWHhISDBIc1Q5VGd6LTVXb1hDellaakhwZnpMMmp3M2s5cExqZ1B3OXJ6Snp5MERsRVdDR0FQZ9IBWEFVX3lxTFBLZ2tUWlN2eENwamNEdUhmQU03SWYzWlpheElDbVQ0ZEZvdmt0TnFmMHp3QXU3VlE1ZkRSWEVIamMwUEFVd3NSU2IyVnlCX3h0anlleW40NDY?oc=5",
          "snippet": "",
          "source": "아주경제",
          "sources": [
            {
              "name": "아주경제",
              "url": "https://news.google.com/rss/articles/CBMiWkFVX3lxTFBtay1YWjZiTUNJV0RYRFRVeTlOVDNuVlRWaXVyWHhISDBIc1Q5VGd6LTVXb1hDellaakhwZnpMMmp3M2s5cExqZ1B3OXJ6Snp5MERsRVdDR0FQZ9IBWEFVX3lxTFBLZ2tUWlN2eENwamNEdUhmQU03SWYzWlpheElDbVQ0ZEZvdmt0TnFmMHp3QXU3VlE1ZkRSWEVIamMwUEFVd3NSU2IyVnlCX3h0anlleW40NDY?oc=5",
              "origin": "google"
            }
          ],
          "source_count": 1,
          "published": "2026-07-24T16:49:51+09:00",
          "ts": 1784879391.0,
          "group": "governor",
          "group_label": "경기도지사"
        },
        {
          "title": "경기도, 내년 주요 현안 국비 지원 건의…지방재정 제도 개선도 제안",
          "url": "https://www.pressian.com/pages/articles/2026072416474720572?utm_source=naver&utm_medium=search",
          "snippet": "추미애 지사, 박홍근 기획예산처 장관 만나 '4219억원 규모' 반영 요청 경기도가 교통 인프라 확충 등 주요... 24일 도에 따르면 추미애 지사는 이날 정부서울청사에서 박홍근 기획예산처 장관을 만나 경기도 주요...",
          "source": "프레시안",
          "sources": [
            {
              "name": "프레시안",
              "url": "https://www.pressian.com/pages/articles/2026072416474720572?utm_source=naver&utm_medium=search",
              "origin": "naver"
            }
          ],
          "source_count": 1,
          "published": "2026-07-24T16:49:00+09:00",
          "ts": 1784879340.0,
          "group": "governor",
          "group_label": "경기도지사"
        },
        {
          "title": "합수본 '신천지 민주당 당원 가입' 수사로 민주당 혼란 가중 : 최민희 \"...",
          "url": "https://www.huffingtonpost.kr/article/258991",
          "snippet": "후보, 추미애 경기지사 후보가 모두 신천지가 만들어낸 후보들이냐. 이런 자폭 테러, 해당 행동이 어디 있단 말이냐\"라고 비판했다. 반면 친석(친김민석)계인 강득구 최고위원은 \"이제 사실관계를 확인하고 책임있게 판단할...",
          "source": "huffingtonpost.kr",
          "sources": [
            {
              "name": "huffingtonpost.kr",
              "url": "https://www.huffingtonpost.kr/article/258991",
              "origin": "naver"
            }
          ],
          "source_count": 1,
          "published": "2026-07-24T16:46:00+09:00",
          "ts": 1784879160.0,
          "group": "governor",
          "group_label": "경기도지사"
        },
        {
          "title": "추미애 경기지사, 정부에 재정분권 개선 건의…국비 확보 행보 본격화",
          "url": "https://www.discoverynews.kr/news/articleView.html?idxno=1096963",
          "snippet": "경기도는 24일 추미애 지사가 정부서울청사에서 박홍근 기획예산처 장관을 만나 재정분권 강화 방안과 2027년도 주요 국비사업 지원 필요성을 설명하고 정부 차원의 협조를 요청했다고 밝혔다. 도는 면담에서 지방재정이...",
          "source": "discoverynews.kr",
          "sources": [
            {
              "name": "discoverynews.kr",
              "url": "https://www.discoverynews.kr/news/articleView.html?idxno=1096963",
              "origin": "naver"
            }
          ],
          "source_count": 1,
          "published": "2026-07-24T16:42:00+09:00",
          "ts": 1784878920.0,
          "group": "governor",
          "group_label": "경기도지사"
        },
        {
          "title": "추미애 \"경기도 재정구조 취약\"…정부에 제도개선·국비 지원 요청",
          "url": "https://www.news1.kr/local/gyeonggi/6238362",
          "snippet": "추미애 경기도지사가 정부에 지방재정 제도 개선과 함께 경기남부광역철도의 제5차 국가철도망 구축계획 반영, 도내 주요 현안사업에 대한 국비 지원을 요청했다. 24일 경기도에 따르면 추 지사는 이날...",
          "source": "뉴스1",
          "sources": [
            {
              "name": "뉴스1",
              "url": "https://www.news1.kr/local/gyeonggi/6238362",
              "origin": "naver"
            }
          ],
          "source_count": 1,
          "published": "2026-07-24T16:41:00+09:00",
          "ts": 1784878860.0,
          "group": "governor",
          "group_label": "경기도지사"
        },
        {
          "title": "'1호 청원' 응답 나선 추미애, 경기남부 광역철도 반영 총력전",
          "url": "https://www.nocutnews.co.kr/news/6553061?utm_source=naver&utm_medium=article&utm_campaign=20260724043710",
          "snippet": "추미애 경기지사가 다음 달 민선9기 첫 도민 청원 답변으로 낼 예정인 경기남부 광역철도 사업을 정부 사업으로 반영해달라며 적극 설득에 나섰다. 24일 경기도에 따르면 추 지사는 이날 박홍근 기획예산처 장관을...",
          "source": "노컷뉴스",
          "sources": [
            {
              "name": "노컷뉴스",
              "url": "https://www.nocutnews.co.kr/news/6553061?utm_source=naver&utm_medium=article&utm_campaign=20260724043710",
              "origin": "naver"
            }
          ],
          "source_count": 1,
          "published": "2026-07-24T16:38:00+09:00",
          "ts": 1784878680.0,
          "group": "governor",
          "group_label": "경기도지사"
        },
        {
          "title": "추미애, 기획예산처 장관에 4천억 규모 국비 반영 요청",
          "url": "https://www.yna.co.kr/view/AKR20260724139900061?input=1195m",
          "snippet": "추미애 경기도지사는 24일 정부서울청사에서 박홍근 기획예산처 장관을 만나 경기도 현안 사업의 국비 반영 등 재정위기 극복을 위한 협조를 요청했다. 추 지사가 정부 예산안에 반영을 요청한 2027년 주요 사업은...",
          "source": "연합뉴스",
          "sources": [
            {
              "name": "연합뉴스",
              "url": "https://www.yna.co.kr/view/AKR20260724139900061?input=1195m",
              "origin": "naver"
            }
          ],
          "source_count": 1,
          "published": "2026-07-24T16:37:00+09:00",
          "ts": 1784878620.0,
          "group": "governor",
          "group_label": "경기도지사"
        },
        {
          "title": "\"이대로는 안 된다\" 4천억 국비 깃발 든 추미애…박홍근 찾아 총력전",
          "url": "https://www.g-enews.com/view.php?ud=2026072415530618108fbfc802b3_1",
          "snippet": "추미애 경기도지사는 24일 정부서울청사에서 박홍근 기획예산처 장관을 만나 도내 핵심 현안의 당위성을 설명하고, 2027년도 정부 예산안에 약 4천억 원 규모의 국비를 반영해 줄 것을 강력히 요청했다. 이번 회동은...",
          "source": "g-enews.com",
          "sources": [
            {
              "name": "g-enews.com",
              "url": "https://www.g-enews.com/view.php?ud=2026072415530618108fbfc802b3_1",
              "origin": "naver"
            }
          ],
          "source_count": 1,
          "published": "2026-07-24T16:28:00+09:00",
          "ts": 1784878080.0,
          "group": "governor",
          "group_label": "경기도지사"
        },
        {
          "title": "추미애 경기도지사, 국비 4천억 지원",
          "url": "https://www.sentv.co.kr/article/view/sentv202607240158",
          "snippet": "추미애 경기도지사가 정부서울청사에서 박홍근 기획예산처 장관을 만나 내년도 국비 4천억 원 반영과 지방재정 제도 개선을 요청했습니다. 추 지사는 취득세 감소와 복지예산 증가로 재정 부담이 커지고 있다며...",
          "source": "sentv.co.kr",
          "sources": [
            {
              "name": "sentv.co.kr",
              "url": "https://www.sentv.co.kr/article/view/sentv202607240158",
              "origin": "naver"
            }
          ],
          "source_count": 1,
          "published": "2026-07-24T16:24:00+09:00",
          "ts": 1784877840.0,
          "group": "governor",
          "group_label": "경기도지사"
        },
        {
          "title": "추미애 \"청년 월세 지원 확대하고 3기 신도시 지연 해소해야\"",
          "url": "https://www.newstnt.com/news/articleView.html?idxno=711550",
          "snippet": "추미애 경기도지사가 청년 월세와 매입임대주택 지원 확대, 주거취약계층 실태조사, 3기 신도시 개발 지연 해소를 주문했다. 추 지사는 23일 오후 경기도청 서희홀에서 열린 도시주택실·도시개발국 업무보고에서 \"주거권은...",
          "source": "newstnt.com",
          "sources": [
            {
              "name": "newstnt.com",
              "url": "https://www.newstnt.com/news/articleView.html?idxno=711550",
              "origin": "naver"
            }
          ],
          "source_count": 1,
          "published": "2026-07-24T16:20:00+09:00",
          "ts": 1784877600.0,
          "group": "governor",
          "group_label": "경기도지사"
        },
        {
          "title": "추미애 \"경기남부광역철도 예타 경제성 가장 높을 것\"…제5차 국가철도...",
          "url": "https://www.dailian.co.kr/news/view/1670712/?sc=Naver",
          "snippet": "추미애 경기도지사가 제5차 국가철도망 구축계획에 경기남부광역철도 반영을 집중 요청하며, 재정위기 극복을 위한 지방재정 제도개선과 4천억 원 규모의 국비 지원 협조를 함께 건의했다. 추 지사는 24일 정부서울청사...",
          "source": "dailian.co.kr",
          "sources": [
            {
              "name": "dailian.co.kr",
              "url": "https://www.dailian.co.kr/news/view/1670712/?sc=Naver",
              "origin": "naver"
            }
          ],
          "source_count": 1,
          "published": "2026-07-24T16:12:00+09:00",
          "ts": 1784877120.0,
          "group": "governor",
          "group_label": "경기도지사"
        },
        {
          "title": "[경기] 경기도, 이주민 주거취약 4,400여 곳 전수조사 착수",
          "url": "https://www.ytn.co.kr/_ln/0115_202607241612456337",
          "snippet": "추미애 경기도지사는 폭염을 비롯한 재난이 주거 취약계층에게 더 큰 위험이 된다며 이주민들이 안전한 환경에서 생활할 수 있도록 보호 안전망을 빈틈없이 구축하겠다고 밝혔습니다.",
          "source": "YTN",
          "sources": [
            {
              "name": "YTN",
              "url": "https://www.ytn.co.kr/_ln/0115_202607241612456337",
              "origin": "naver"
            }
          ],
          "source_count": 1,
          "published": "2026-07-24T16:12:00+09:00",
          "ts": 1784877120.0,
          "group": "governor",
          "group_label": "경기도지사"
        },
        {
          "title": "추미애 지사, 재정위기 극복에 '잰걸음'... 박홍근 기획예산처 장관 만...",
          "url": "https://www.getnews.co.kr/news/articleView.html?idxno=876008",
          "snippet": "추미애 경기도지사는 24일 정부서울청사에서 박홍근 기획예산처 장관을 만나 주요 현안사업에 대해 설명하고, 4천억 원 규모의 국비 지원을 요청하는 등 재정 확보를 위한 행보에 박차를 가하고 있다. 추미애 지사는...",
          "source": "getnews.co.kr",
          "sources": [
            {
              "name": "getnews.co.kr",
              "url": "https://www.getnews.co.kr/news/articleView.html?idxno=876008",
              "origin": "naver"
            }
          ],
          "source_count": 1,
          "published": "2026-07-24T16:10:00+09:00",
          "ts": 1784877000.0,
          "group": "governor",
          "group_label": "경기도지사"
        },
        {
          "title": "추미애 경기지사, 지방재정 구조개혁 승부수…국비 4000억원 확보 나서",
          "url": "http://www.fieldnews.kr/news/articleView.html?idxno=30202",
          "snippet": "추미애 경기도지사가 정부를 상대로 지방재정 구조 개선과 주요 현안사업 국비 확보에 직접 나섰다. 취득세 감소와 복지지출 증가로 재정 부담이 커진 경기도의 현실을 설명하며 제도 개선과 함께 내년도 4000억원...",
          "source": "fieldnews.kr",
          "sources": [
            {
              "name": "fieldnews.kr",
              "url": "http://www.fieldnews.kr/news/articleView.html?idxno=30202",
              "origin": "naver"
            }
          ],
          "source_count": 1,
          "published": "2026-07-24T16:10:00+09:00",
          "ts": 1784877000.0,
          "group": "governor",
          "group_label": "경기도지사"
        },
        {
          "title": "경기도청 직원 \"성적 요구 거절 뒤 상사에게 보복 당했다\" 폭로",
          "url": "https://www.pressian.com/pages/articles/2026072416013154954?utm_source=naver&utm_medium=search",
          "snippet": "추미애 지사, 피해자 보호 및 2차 가해 철저 차단·엄정 처분 지시 경기도청 내부에서 상사의 성적 요구를... 이 같은 사실이 알려지자 추미애 경기도지사는 즉각적인 조치를 지시했다. 추 지사는 이날 특별지시를 통해 \"최근...",
          "source": "프레시안",
          "sources": [
            {
              "name": "프레시안",
              "url": "https://www.pressian.com/pages/articles/2026072416013154954?utm_source=naver&utm_medium=search",
              "origin": "naver"
            }
          ],
          "source_count": 1,
          "published": "2026-07-24T16:02:00+09:00",
          "ts": 1784876520.0,
          "group": "governor",
          "group_label": "경기도지사"
        }
      ]
    },
    {
      "id": "gg_council",
      "label": "경기도의회(문체·미래위)",
      "priority": 4,
      "count": 14,
      "items": [
        {
          "title": "경기도의회, 도·도교육청 예결특위원장 백승기·이채명 의원…원구성 ...",
          "url": "https://www.kihoilbo.co.kr/news/articleView.html?idxno=3029769",
          "snippet": "기호일보, KIHOILBO 경기도의회 전경 제12대 경기도의회가 도청·도교육청 예산결산특별위원회와... (화성1), 미래과학협력위 김태형(화성5), 여성가족평생교육위 김용성(광명4), 교육기획위 국중범(성남4), 교육행정위...",
          "source": "기호일보",
          "sources": [
            {
              "name": "기호일보",
              "url": "https://www.kihoilbo.co.kr/news/articleView.html?idxno=3029837",
              "origin": "naver"
            },
            {
              "name": "vop.co.kr",
              "url": "https://vop.co.kr/A00001695951.html",
              "origin": "naver"
            },
            {
              "name": "econonews.co.kr",
              "url": "http://www.econonews.co.kr/news/articleView.html?idxno=441769",
              "origin": "naver"
            },
            {
              "name": "kpinews.kr",
              "url": "https://www.kpinews.kr/newsView/1065597651184486",
              "origin": "naver"
            }
          ],
          "source_count": 4,
          "published": "2026-07-23T16:30:00+09:00",
          "ts": 1784791800.0,
          "group": "gg_council",
          "group_label": "경기도의회(문체·미래위)"
        },
        {
          "title": "안시현 경기도의원, 동두천 대표축제 신뢰 높이며 문체위 활동 첫발",
          "url": "https://www.seoul.co.kr/news/publicnews/local_govern/kyungki_do/2026/07/24/20260724500034?wlog_tag3=naver",
          "snippet": "경기도의회 문화체육관광위원회 안시현 의원(더불어민주당, 동두천1)이 지역 대표 축제의 공정성을 바로잡고 청년·신인 예술인의 참여 기회를 보장하기 위한 본격적인 의정활동에 나섰다. 안시현 의원은 지난 21일 열린...",
          "source": "서울신문",
          "sources": [
            {
              "name": "서울신문",
              "url": "https://www.seoul.co.kr/news/publicnews/local_govern/kyungki_do/2026/07/24/20260724500034?wlog_tag3=naver",
              "origin": "naver"
            },
            {
              "name": "경기포커스",
              "url": "https://news.google.com/rss/articles/CBMibEFVX3lxTFA0LVVaVzZUVVdpZDNrU3BNcHRJT3pNUTQwRmxCc1NoMDhXdDNSQkRwSFNsejNMcUlHZS1GZnVyUzV2Y1dHX2VscW9YdFNxYmRPX2NKMDNLeUVtSGtJUVlpc2VVbzR2TW1XQnZ5dg?oc=5",
              "origin": "google"
            },
            {
              "name": "네이트",
              "url": "https://news.google.com/rss/articles/CBMiU0FVX3lxTE1oZ1NSVGF0LUJOSUdoQUZLOTJVTGdpdUV0cnplSHNESEk1VnNJVHkwdjhYZEhQVzFtaTZyTGFQWURMZW5ZeHJIQVljSldkR0oxd2Fz?oc=5",
              "origin": "google"
            }
          ],
          "source_count": 3,
          "published": "2026-07-24T09:13:00+09:00",
          "ts": 1784851980.0,
          "group": "gg_council",
          "group_label": "경기도의회(문체·미래위)"
        },
        {
          "title": "경기도의회 안시현 의원, 동두천 락페스티벌 심사·운영 공정성 확보 촉...",
          "url": "https://www.kmaeil.com/news/articleView.html?idxno=646577",
          "snippet": "경기도의회 문화체육관광위원회 안시현 의원이 동두천 대표축제에 대한 신뢰를 높이고 청년·신인 예술인의 참여 기회를 넓히기 위한 의정활동의 첫발을 내디뎠다. 안 의원은 지난 21일 제392회 임시회 제2차...",
          "source": "kmaeil.com",
          "sources": [
            {
              "name": "kmaeil.com",
              "url": "https://www.kmaeil.com/news/articleView.html?idxno=646577",
              "origin": "naver"
            },
            {
              "name": "tournews21.com",
              "url": "https://www.tournews21.com/news/articleView.html?idxno=139212",
              "origin": "naver"
            }
          ],
          "source_count": 2,
          "published": "2026-07-24T17:36:00+09:00",
          "ts": 1784882160.0,
          "group": "gg_council",
          "group_label": "경기도의회(문체·미래위)"
        },
        {
          "title": "경기도의회 미래과학협력위원회, 경기 AI 혁신클러스터 기업 교류회 ‘...",
          "url": "https://www.seoul.co.kr/news/publicnews/local_govern/kyungki_do/2026/07/23/20260723500251?wlog_tag3=naver",
          "snippet": "경기도의회 미래과학협력위원회(위원장 김태형, 더불어민주당, 화성5)가 AI 산업 현장의 목소리를 듣고 관련 스타트업 및 전문가들과 소통하는 자리를 가졌다. 미래과학협력위원회는 22일 경기스타트업캠퍼스에서...",
          "source": "서울신문",
          "sources": [
            {
              "name": "서울신문",
              "url": "https://www.seoul.co.kr/news/publicnews/local_govern/kyungki_do/2026/07/23/20260723500251?wlog_tag3=naver",
              "origin": "naver"
            },
            {
              "name": "전국매일신문",
              "url": "https://news.google.com/rss/articles/CBMibkFVX3lxTFB1UHJBZ0VxZnNzNG1TQ25OalFtaE9YYllaTnlicWtfcFZuU1hUNlRLSW4yaTM3OW03Y3JIc0YycDNRbktwcmpxajhJdWZoVmVpaWRtSEhzVlZjOVA2WlRvTld2Z3B6TUxRVnJZdFVR?oc=5",
              "origin": "google"
            }
          ],
          "source_count": 2,
          "published": "2026-07-23T17:15:00+09:00",
          "ts": 1784794500.0,
          "group": "gg_council",
          "group_label": "경기도의회(문체·미래위)"
        },
        {
          "title": "유호준 경기도의원 “경기동북부 로봇산업 거점 육성, 지원책 나와야”",
          "url": "https://www.seoul.co.kr/news/publicnews/local_govern/kyungki_do/2026/07/24/20260724500285?wlog_tag3=naver",
          "snippet": "경기도의회 미래과학협력위원회 유호준 의원(더불어민주당, 남양주 다산1동)은 21일 열린 제392회 임시회 제1차 미래과학협력위원회 회의에서 추미애 지사가 선거 과정에서 약속한 권역별 산업 육성 공약에 대해...",
          "source": "서울신문",
          "sources": [
            {
              "name": "서울신문",
              "url": "https://www.seoul.co.kr/news/publicnews/local_govern/kyungki_do/2026/07/24/20260724500285?wlog_tag3=naver",
              "origin": "naver"
            }
          ],
          "source_count": 1,
          "published": "2026-07-24T16:41:00+09:00",
          "ts": 1784878860.0,
          "group": "gg_council",
          "group_label": "경기도의회(문체·미래위)"
        },
        {
          "title": "이병숙 경기도의원, 영동초 교육환경 개선 위한 현장 정담회 참석",
          "url": "https://www.seoul.co.kr/news/publicnews/local_govern/kyungki_do/2026/07/24/20260724500215?wlog_tag3=naver",
          "snippet": "경기도의회 문화체육관광위원회 이병숙 의원(더불어민주당, 수원12)이 지난 23일 영동초등학교 회의실에서 ‘교육환경개선 정담회’를 열고 노후 시설 교체 및 수업용 기자재 확충 방안을 심도 있게 논의했다. 간담회에...",
          "source": "서울신문",
          "sources": [
            {
              "name": "서울신문",
              "url": "https://www.seoul.co.kr/news/publicnews/local_govern/kyungki_do/2026/07/24/20260724500215?wlog_tag3=naver",
              "origin": "naver"
            }
          ],
          "source_count": 1,
          "published": "2026-07-24T14:38:00+09:00",
          "ts": 1784871480.0,
          "group": "gg_council",
          "group_label": "경기도의회(문체·미래위)"
        },
        {
          "title": "김영희·전예슬 경기도의원, 교육과 문화를 축으로 시민이 체감하는 변...",
          "url": "https://www.seoul.co.kr/news/publicnews/local_govern/kyungki_do/2026/07/24/20260724500211?wlog_tag3=naver",
          "snippet": "경기도의회 김영희 의원(더불어민주당, 오산1)과 전예슬 의원(더불어민주당, 오산2)이 경기도의회... 문화체육관광위원회 소속 전예슬 의원은 문화·체육·관광 정책을 활성화해 시민의 일상 속 삶의 질을 한층 높이고, 지역...",
          "source": "서울신문",
          "sources": [
            {
              "name": "서울신문",
              "url": "https://www.seoul.co.kr/news/publicnews/local_govern/kyungki_do/2026/07/24/20260724500211?wlog_tag3=naver",
              "origin": "naver"
            }
          ],
          "source_count": 1,
          "published": "2026-07-24T14:34:00+09:00",
          "ts": 1784871240.0,
          "group": "gg_council",
          "group_label": "경기도의회(문체·미래위)"
        },
        {
          "title": "임창휘 경기도의원 “경기 남부 IT·로봇 기술, 북부 제조업에 이식해야...",
          "url": "https://www.seoul.co.kr/news/publicnews/local_govern/kyungki_do/2026/07/24/20260724500195?wlog_tag3=naver",
          "snippet": "경기도의회 미래과학협력위원회 임창휘 의원(더불어민주당, 광주2)이 도내 남·북부 간 심각한 산업 불균형을 해소하기 위한 정책 대안을 제시했다. 임 의원은 지난 21일 열린 경기테크노파크(이하 경기TP) 및...",
          "source": "서울신문",
          "sources": [
            {
              "name": "서울신문",
              "url": "https://www.seoul.co.kr/news/publicnews/local_govern/kyungki_do/2026/07/24/20260724500195?wlog_tag3=naver",
              "origin": "naver"
            }
          ],
          "source_count": 1,
          "published": "2026-07-24T13:59:00+09:00",
          "ts": 1784869140.0,
          "group": "gg_council",
          "group_label": "경기도의회(문체·미래위)"
        },
        {
          "title": "임창휘 경기도의원 “융기원 연구 성과, 대학 넘어 도민·기업에 직접 체...",
          "url": "https://www.seoul.co.kr/news/publicnews/local_govern/kyungki_do/2026/07/24/20260724500123?wlog_tag3=naver",
          "snippet": "경기도의회 미래과학협력위원회 임창휘 의원(더불어민주당, 광주 2)이 차세대융합기술연구원(이하 융기원)의 첨단 연구개발(R＆D) 결실이 대학이나 특정 연구진에 그치지 않고 도민과 지역 기업, 청년들에게 실질적인...",
          "source": "서울신문",
          "sources": [
            {
              "name": "서울신문",
              "url": "https://www.seoul.co.kr/news/publicnews/local_govern/kyungki_do/2026/07/24/20260724500123?wlog_tag3=naver",
              "origin": "naver"
            }
          ],
          "source_count": 1,
          "published": "2026-07-24T10:56:00+09:00",
          "ts": 1784858160.0,
          "group": "gg_council",
          "group_label": "경기도의회(문체·미래위)"
        },
        {
          "title": "경기도의회, 3개 특위 위원장 선출… ‘제12대 전반기 원 구성’ 마무리",
          "url": "https://www.pressian.com/pages/articles/2026072318153688698?utm_source=naver&utm_medium=search",
          "snippet": "제12대 경기도의회가 3개 특별위원회의 위원장을 선출을 끝으로 전반기 원 구성을 완료했다. 23일 도의회에... (민·평택1) △문화체육관광위원회 채신덕(민·김포2) △보건복지위원회 김동규(민·안산1)...",
          "source": "프레시안",
          "sources": [
            {
              "name": "프레시안",
              "url": "https://www.pressian.com/pages/articles/2026072318153688698?utm_source=naver&utm_medium=search",
              "origin": "naver"
            }
          ],
          "source_count": 1,
          "published": "2026-07-23T18:17:00+09:00",
          "ts": 1784798220.0,
          "group": "gg_council",
          "group_label": "경기도의회(문체·미래위)"
        },
        {
          "title": "임창휘 경기도의원 “판교 성공모델 도 전역 확장하고, 3기 신도시를 거...",
          "url": "https://www.seoul.co.kr/news/publicnews/local_govern/kyungki_do/2026/07/23/20260723500269?wlog_tag3=naver",
          "snippet": "경기도의회 미래과학협력위원회 임창휘 의원(더불어민주당, 광주2)은 지난 21일 진행된 경기도경제과학진흥원(이하 경과원) 업무보고에서, 세계적으로 인정받는 ‘판교 테크노밸리’의 성공 역사를 경기도 전체로...",
          "source": "서울신문",
          "sources": [
            {
              "name": "서울신문",
              "url": "https://www.seoul.co.kr/news/publicnews/local_govern/kyungki_do/2026/07/23/20260723500269?wlog_tag3=naver",
              "origin": "naver"
            }
          ],
          "source_count": 1,
          "published": "2026-07-23T17:34:00+09:00",
          "ts": 1784795640.0,
          "group": "gg_council",
          "group_label": "경기도의회(문체·미래위)"
        },
        {
          "title": "\"연구실 안에 갇힌 성과, 도민에겐 남 얘기\"…임창휘 도의원, 융기원 정...",
          "url": "https://www.etoday.co.kr/news/view/2606711",
          "snippet": "경기도 및 유관기관과 적극적으로 협의해 개선책을 마련하겠다\"고 답변했다. 임창휘 의원은 \"경기도 유일의 첨단 R&D 실증기관인 융기원이 도민의 삶을 바꾸는 과학기술 거점으로 거듭날 수 있도록 미래과학협력위원회...",
          "source": "etoday.co.kr",
          "sources": [
            {
              "name": "etoday.co.kr",
              "url": "https://www.etoday.co.kr/news/view/2606711",
              "origin": "naver"
            }
          ],
          "source_count": 1,
          "published": "2026-07-23T15:10:00+09:00",
          "ts": 1784787000.0,
          "group": "gg_council",
          "group_label": "경기도의회(문체·미래위)"
        },
        {
          "title": "김영희·전예슬 경기도의원, 오산상담소서 손잡았다…\"교육·문화 두 축...",
          "url": "https://www.etoday.co.kr/news/view/2606708",
          "snippet": "김영희·전예슬 경기도의회 의원이 오산상담소를 거점으로 시민 밀착 의정에 나선다. 교육기획위원회와 문화체육관광위원회에 각각 자리 잡은 두 의원이 교육과 문화를 양대 축으로 삼아 시민이 피부로 느끼는 변화를...",
          "source": "etoday.co.kr",
          "sources": [
            {
              "name": "etoday.co.kr",
              "url": "https://www.etoday.co.kr/news/view/2606708",
              "origin": "naver"
            }
          ],
          "source_count": 1,
          "published": "2026-07-23T15:06:00+09:00",
          "ts": 1784786760.0,
          "group": "gg_council",
          "group_label": "경기도의회(문체·미래위)"
        },
        {
          "title": "최규진 도의원 \"'지지부진' 문화재단·관광공사 고양 이전, 구체적 로드...",
          "url": "http://www.mygoyang.com/news/articleView.html?idxno=89610",
          "snippet": "20일 열린 경기도의회 문화체육관광위원회 업무보고에서 최규진 의원이 경기문화재단과 경기관광공사의 고양시 이전 추진 상황을 점검하고 있다. 경기도의회 제공. 경기도의회 문화체육관광위원회 소속 최규진 의원...",
          "source": "mygoyang.com",
          "sources": [
            {
              "name": "mygoyang.com",
              "url": "http://www.mygoyang.com/news/articleView.html?idxno=89610",
              "origin": "naver"
            }
          ],
          "source_count": 1,
          "published": "2026-07-23T13:48:00+09:00",
          "ts": 1784782080.0,
          "group": "gg_council",
          "group_label": "경기도의회(문체·미래위)"
        }
      ]
    },
    {
      "id": "bucheon",
      "label": "부천시(콘텐츠 관련)",
      "priority": 5,
      "count": 1,
      "items": [
        {
          "title": "국립순천대 문예창작학전공, 부천국제판타스틱영화제 찾아 현장형 교육...",
          "url": "http://www.newsmaker.or.kr/news/articleView.html?idxno=179583",
          "snippet": "국립순천대학교 문예창작학전공이 '2026년 RISE사업 G1 글로벌 지역특화 인재양성 선진기술·선진기관 교육 및 견학 프로그램'의 일환으로 부천국제판타스틱영화제와 문화예술 기관을 방문했다. 이번 프로그램은 지난 7월...",
          "source": "newsmaker.or.kr",
          "sources": [
            {
              "name": "newsmaker.or.kr",
              "url": "http://www.newsmaker.or.kr/news/articleView.html?idxno=179583",
              "origin": "naver"
            },
            {
              "name": "베리타스알파",
              "url": "https://news.google.com/rss/articles/CBMibEFVX3lxTE1sXzd3V2xuekpocVJzZUc3ZFljS040NnRTdmp5ZlNiY3M4NXRpWW1hdVFtd0psWVg3V1l5VE5UaEl3cHVPanFYNVo3N2pOcFptLUJqZFJKTVVmcGpGamFRR0tSYl9TNnBXaV9hRg?oc=5",
              "origin": "google"
            }
          ],
          "source_count": 2,
          "published": "2026-07-24T14:34:00+09:00",
          "ts": 1784871240.0,
          "group": "bucheon",
          "group_label": "부천시(콘텐츠 관련)"
        }
      ]
    },
    {
      "id": "bucheon_council",
      "label": "부천시의회(재정문화위)",
      "priority": 6,
      "count": 2,
      "items": [
        {
          "title": "부천시의회 ‘부천아트벙커B39’ 점검",
          "url": "https://www.siminilbo.co.kr/news/newsview.php?ncode=1160271370076221",
          "snippet": "[사진=부천시의회 제공] 부천시의회 재정문화위원회(위원장 윤단비)가 21일 부천아트벙커B39를 방문, 운영 실태를 점검했다. 부천아트벙커B39는 1995년부터 운영되다 2013년 폐쇄된 삼정동 소각장을 리모델링해 조성한...",
          "source": "siminilbo.co.kr",
          "sources": [
            {
              "name": "siminilbo.co.kr",
              "url": "https://www.siminilbo.co.kr/news/newsview.php?ncode=1160271370076221",
              "origin": "naver"
            },
            {
              "name": "뉴시스",
              "url": "https://www.newsis.com/view/NISX20260723_0003720432",
              "origin": "naver"
            },
            {
              "name": "gukjenews.com",
              "url": "https://news.google.com/rss/articles/CBMibkFVX3lxTE82MEw5aDZkX3NxNDRjaUZmbTRSTWxweVZuMW90c0tJRHJ5elJCNUxCcjc2Z0NXTHhvMkozbEItdG0wN2RVVHJrS0RSaU0xajFFS3JTOThBUWkxN2dLR2dpN1UtVy1FUHhZX09LdlVB?oc=5",
              "origin": "google"
            },
            {
              "name": "동방일보",
              "url": "https://news.google.com/rss/articles/CBMickFVX3lxTE8xb3loWnlwVjhMbU9rSGVCalhYNWI1R182SVZCQ1dieE4xTTV2LTlxZHhuZFB5UEx5VkhYUWVYamFidElPcGpYUlZ2TEc3bHh6YTc1bmJfeVBzQXZER2RKVjJSdEpZeThkdVBLTjcyVVE5Zw?oc=5",
              "origin": "google"
            },
            {
              "name": "한국사회복지저널",
              "url": "https://news.google.com/rss/articles/CBMia0FVX3lxTFBNTHZwaHRacnZLWGwxWjJHWGI0enFyQ0FPVkd6bkxDVDJJRmtjbGxBenF6UHdFcmJ2U2FkbS1FbV9RaHQ4dVg4V1A3ZHdzcTQyZ2hIeXRhMUo1cFRHZTV4b2JVdHhNX05GdS1j?oc=5",
              "origin": "google"
            }
          ],
          "source_count": 5,
          "published": "2026-07-23T17:22:00+09:00",
          "ts": 1784794920.0,
          "group": "bucheon_council",
          "group_label": "부천시의회(재정문화위)"
        },
        {
          "title": "부천시의회 재정문화위, 아트벙커B39 현장점검",
          "url": "https://www.gukjenews.com/news/articleView.html?idxno=3644687",
          "snippet": "부천시의회 재정문화위원회가 제10대 의회 출범 이후 첫 현장방문으로 부천아트벙커B39를 찾았다. 사진=부천시의회 부천시의회 재정문화위원회가 제10대 의회 출범 이후 첫 현장방문으로 부천아트벙커B39를 찾았다....",
          "source": "국제뉴스",
          "sources": [
            {
              "name": "국제뉴스",
              "url": "https://www.gukjenews.com/news/articleView.html?idxno=3645683",
              "origin": "naver"
            }
          ],
          "source_count": 1,
          "published": "2026-07-23T21:54:00+09:00",
          "ts": 1784811240.0,
          "group": "bucheon_council",
          "group_label": "부천시의회(재정문화위)"
        }
      ]
    },
    {
      "id": "central",
      "label": "중앙부처(콘텐츠)",
      "priority": 7,
      "count": 19,
      "items": [
        {
          "title": "넵튠, 콘진원 K컬처 글로벌 정부 과제 선정... 생성형 AI로 웹툰 IP 게임...",
          "url": "https://www.etnews.com/20260724000246",
          "snippet": "넵튠이 한국콘텐츠진흥원 'K컬처 글로벌 스타트업 육성 기술 개발' 과제 수행 기업으로 선정됐다. 이번 과제는 슈퍼플래닛, 콘텐츠퍼스트, 고려대학교 인공지능학과 지능형 영상처리 연구실과 컨소시엄을 구성해...",
          "source": "전자신문",
          "sources": [
            {
              "name": "전자신문",
              "url": "https://www.etnews.com/20260724000246",
              "origin": "naver"
            },
            {
              "name": "megaeconomy.co.kr",
              "url": "https://www.megaeconomy.co.kr/news/newsview.php?ncode=1065590637352204",
              "origin": "naver"
            },
            {
              "name": "쿠키뉴스",
              "url": "https://www.kukinews.com/article/view/kuk202607240060",
              "origin": "naver"
            },
            {
              "name": "viva100.com",
              "url": "https://www.viva100.com/article/20260724500279",
              "origin": "naver"
            },
            {
              "name": "asiaa.co.kr",
              "url": "https://www.asiaa.co.kr/news/articleView.html?idxno=256296",
              "origin": "naver"
            },
            {
              "name": "경향신문",
              "url": "https://sports.khan.co.kr/article/202607241037003?pt=nv",
              "origin": "naver"
            },
            {
              "name": "지디넷코리아",
              "url": "https://zdnet.co.kr/view/?no=20260724102903",
              "origin": "naver"
            },
            {
              "name": "digitaltoday.co.kr",
              "url": "https://www.digitaltoday.co.kr/news/articleView.html?idxno=686614",
              "origin": "naver"
            },
            {
              "name": "betanews.net",
              "url": "https://www.betanews.net/article/view/beta202607240006",
              "origin": "naver"
            },
            {
              "name": "네이트",
              "url": "https://news.google.com/rss/articles/CBMieEFVX3lxTE1rVEZLelUwZ1ZRQzB2a2NuSFB0aEFaeDRxUUNNYm84RkhQRHNfTV9OcW5UdmdyNXFKb3dRcURGMUtvTVBlSkJDYU1EWGNYN1o0WVFHTWhNU0hsX1hJQlUwZ0JfZ2oxS1ZadVhYRjhDQzNoR25pSUlBNw?oc=5",
              "origin": "google"
            },
            {
              "name": "아시아에이",
              "url": "https://news.google.com/rss/articles/CBMiakFVX3lxTE4xamtVZWxmVUlLc1hVU1ZxVTcwM2JIWktjLTFjMVV0ZmN3RVFtUkNJYUJMT04zdUd1SzRHOFVWWVVoejBZUHE0bHpEMHBIR1BzZS02NC0wNkVNWnVOV1VrMy1pbmF5ZVdpQ0HSAW5BVV95cUxOWVpvSzJWT1BNTkZzaHk1RGVGbW1BdXhUT0ZaM2xrSHdsWFRpMEdiZDBkci1BMTdKekgtUzBscDR1NkU5a1g4VGlBbEJzYzJDX09lTEt1eVBzUjJBSnB0QUY0Ui1iUGZwWnlGVEFidw?oc=5",
              "origin": "google"
            },
            {
              "name": "v.daum.net",
              "url": "https://news.google.com/rss/articles/CBMiT0FVX3lxTFByY2xJa3hHekl3Tk91cXFpOV9yX21rblhlZzd1NUM1b0pubV9MczRXSEhPWWdrTWtXakllbmlEUWRjV2VPT1dwenN5eEVEdms?oc=5",
              "origin": "google"
            },
            {
              "name": "디지털투데이",
              "url": "https://news.google.com/rss/articles/CBMic0FVX3lxTE1kRG5vR21jci01QjhiYmNycTNuQ3hBQWpJWE91SlRFQlB1QUg0clJuMGxaWEluTmRfU1ZtLXM4bktDYTdHanNNVlFmQ2NSMEJDM3RIZF90RUE3VzByTHdSYzhWU2lHQ0toVkt6MmxnaGJLTzQ?oc=5",
              "origin": "google"
            },
            {
              "name": "베타뉴스",
              "url": "https://news.google.com/rss/articles/CBMiZEFVX3lxTFA5OE5GLWRQa3pfRm8zQXJ1V1YyYXdNbVFvSXBFS0ZwbW1kRDV3OUliZjNHZkhMUVRYb0tsdThveU54aUxYLWJrT3VaZ29rREtDSEpvWEtsM2dTSUlLWm9tdEd1aDQ?oc=5",
              "origin": "google"
            }
          ],
          "source_count": 14,
          "published": "2026-07-24T14:44:00+09:00",
          "ts": 1784871840.0,
          "group": "central",
          "group_label": "중앙부처(콘텐츠)"
        },
        {
          "title": "한국저작권위원회, ‘소셜아이어워드 2026’ 공공분야 최우수상 수상",
          "url": "https://www.donga.com/news/Economy/article/all/20260724/134356936/1",
          "snippet": "강석원 한국저작권위원회 위원장은 “이번 수상은 국민이 이해하기 쉬운 저작권 콘텐츠를 꾸준히 제작하고 소통해 온 노력이 인정받은 결과”라며 “앞으로도 변화하는 디지털 환경과 국민의 정보 수요를 반영한...",
          "source": "동아일보",
          "sources": [
            {
              "name": "동아일보",
              "url": "https://www.donga.com/news/Economy/article/all/20260724/134356936/1",
              "origin": "naver"
            },
            {
              "name": "gosiweek.com",
              "url": "https://www.gosiweek.com/article/1065579419449517",
              "origin": "naver"
            },
            {
              "name": "beyondpost.co.kr",
              "url": "http://www.beyondpost.co.kr/view.php?ud=2026072411094859179aeda69934_30",
              "origin": "naver"
            },
            {
              "name": "비욘드포스트",
              "url": "https://news.google.com/rss/articles/CBMifEFVX3lxTE42SjVXNVVUNGVNZ3JYY2xNRjZDZUNUd0lFeE8tbjJFTXd6QXlUdUhFb0djRnZGYVNjTDlLSjY0dEEtVUZHLWVTaGtTd1p3Z01MZmNLNi13V2liVjlWQzdLZ0hYTWFabHpOZVVZSUVNb29ZY0tqd2NIMzhjU2I?oc=5",
              "origin": "google"
            },
            {
              "name": "경남뉴스",
              "url": "https://news.google.com/rss/articles/CBMiaEFVX3lxTFB0UHp4bnJGUWxsS1cyS2ZUalZ2Znl4VW5OVVhzX0g2V2lybXI4QWNOZm5zbnZ0dHQ0Q0YwT1pFSmZuQm9MNHF1UmFPQW8wekJXeVZhZnI5MDBvRmNPMm15bHM4TGZnaDEw?oc=5",
              "origin": "google"
            },
            {
              "name": "단디뉴스",
              "url": "https://news.google.com/rss/articles/CBMia0FVX3lxTE1pYWNoS2ZnOExKMFRnVUpKRXJFSU1rRENsczRVWFFyTkE5TklJcEhUUW82d3docFA0cno5VXExYnlzbWRxM2h6TGtGUkFyWmZhQ3Mxal9YekM1OVpoUGNSd0puUkVkelBraVc0?oc=5",
              "origin": "google"
            }
          ],
          "source_count": 6,
          "published": "2026-07-24T11:29:00+09:00",
          "ts": 1784860140.0,
          "group": "central",
          "group_label": "중앙부처(콘텐츠)"
        },
        {
          "title": "넵튠, 콘진원 생성형 AI 과제 선정…웹툰 IP 게임 개발 12개월→4개월",
          "url": "https://www.ddaily.co.kr/page/view/2026072410062813802",
          "snippet": "넵튠은 한국콘텐츠진흥원의 'K-컬처 글로벌 스타트업 육성 기술 개발' 과제 수행 기업으로 선정됐다고 24일 밝혔다. 이번 과제는 문화체육관광부와 콘진원이 추진하는 '2026년 문화체육관광 연구개발' 사업의 하나다....",
          "source": "ddaily.co.kr",
          "sources": [
            {
              "name": "ddaily.co.kr",
              "url": "https://www.ddaily.co.kr/page/view/2026072410062813802",
              "origin": "naver"
            },
            {
              "name": "youthdaily.co.kr",
              "url": "https://www.youthdaily.co.kr/news/article.html?no=223670",
              "origin": "naver"
            },
            {
              "name": "네이트",
              "url": "https://news.google.com/rss/articles/CBMiYEFVX3lxTE1Rc19vVERBaDhoWW4yTy1UYVRCaTNzckZoMXVFdUZFdWJqWXBpd3BlX1QwU2dDSW5DYmdraWFPVlF0aERmQzR1TFo4TFRLcWp3ZzVQcmF4UnppM0xLS2xTUA?oc=5",
              "origin": "google"
            },
            {
              "name": "디지털데일리",
              "url": "https://news.google.com/rss/articles/CBMiZEFVX3lxTFBOZ2xHX1dNdUtMYlM2U1hOdFdUUG5DUVRpVFYzTmxKOFVEbzZsQnQxOGpCTloyQWlrVnJ1ZFhUOU9QZmRrdFVoR3lqN0FDMy1US0FxeW5CS0N5M19QaF84aFFxM2w?oc=5",
              "origin": "google"
            },
            {
              "name": "청년일보",
              "url": "https://news.google.com/rss/articles/CBMiZ0FVX3lxTFBLYnpNZDhVc0htS1A4TmRmcUl0SU9Pa3AxREpFNUFnNldLZGxTR2N5OTZobW1EeGtEX1RINHo3a19SbVFSUmRaNnU4VkZxOFNvckRkeW9FMl9aTEVNRVBIekVsc21FUVk?oc=5",
              "origin": "google"
            }
          ],
          "source_count": 5,
          "published": "2026-07-24T10:20:00+09:00",
          "ts": 1784856000.0,
          "group": "central",
          "group_label": "중앙부처(콘텐츠)"
        },
        {
          "title": "넵튠, AI로 웹툰을 게임으로 만든다…77억원 규모 정부 R&D 과제 참여",
          "url": "https://www.sportschosun.com/entertainment/2026-07-24/202607240100148940009492",
          "snippet": "넵튠은 한국콘텐츠진흥원의 'K-Culture 글로벌 스타트업 육성 기술 개발' 과제 수행 기업으로 선정됐다고 24일 밝혔다. 이번 과제는 슈퍼플래닛, 콘텐츠퍼스트, 고려대학교 인공지능학과 지능형 영상처리 연구실과...",
          "source": "sportschosun.com",
          "sources": [
            {
              "name": "sportschosun.com",
              "url": "https://www.sportschosun.com/entertainment/2026-07-24/202607240100148940009492",
              "origin": "naver"
            },
            {
              "name": "game.dailyesports.com",
              "url": "http://game.dailyesports.com/view.php?ud=20260724113050553043da15d9d2_26",
              "origin": "naver"
            },
            {
              "name": "스포츠조선",
              "url": "https://news.google.com/rss/articles/CBMihAFBVV95cUxNempMVWRoWHZrWjNKQVVFMjVDMjJLY0hpaFduc0NSV2JCeHdiR3ZhajhHQXZQNXR1amU1LWdzT3VtTjV6d1BtZWo4STNVcV9LeHFHZkw5S0dzNXdNNFlreHJ2Yk5WVF85MlQyaThHSWdiWXBhRGNDZjRDWk50QnR4czdKcl8?oc=5",
              "origin": "google"
            },
            {
              "name": "네이트",
              "url": "https://news.google.com/rss/articles/CBMiYEFVX3lxTE9CbWpXakt4T2VsUmRnekNRYjM3OEVrZWRyUjlLZk14b1pmZUFxVkhRR0hKLWgyOWFmQmtZeS03VVlNdmhBVVFfMEdJT0hkZzJqWUlFOTc5dkJtbGFSMUpzNg?oc=5",
              "origin": "google"
            }
          ],
          "source_count": 4,
          "published": "2026-07-24T12:38:00+09:00",
          "ts": 1784864280.0,
          "group": "central",
          "group_label": "중앙부처(콘텐츠)"
        },
        {
          "title": "넵튠, 웹툰 게임 자동개발 파이프라인 개발...콘진원 과제 선정",
          "url": "https://www.fomos.kr/redirect/news_view?news_cate_id=2&entry_id=154685",
          "snippet": "넵튠은 한국콘텐츠진흥원의 'K컬처 글로벌 스타트업 육성 기술 개발' 과제 수행 기업으로 선정됐다고 24일 밝혔다. 이번 과제는 슈퍼플래닛, 콘텐츠퍼스트, 고려대학교 인공지능학과 지능형 영상처리 연구실과...",
          "source": "fomos.kr",
          "sources": [
            {
              "name": "fomos.kr",
              "url": "https://www.fomos.kr/redirect/news_view?news_cate_id=2&entry_id=154685",
              "origin": "naver"
            },
            {
              "name": "joongangenews.com",
              "url": "https://www.joongangenews.com/news/articleView.html?idxno=535069",
              "origin": "naver"
            },
            {
              "name": "중소기업신문",
              "url": "https://news.google.com/rss/articles/CBMibkFVX3lxTFB3UDIwY1NEZUFfT3hwWHhpZ2xDOVFRSmJLdm9RazVEeGl3b3M4ZjJJNGtCOVJ5WF96OXVfZ3k5aDR5bjY1Nm5CZEIwcGlneHVBekZia2wzN3A3TXZVUnJjT3dUV0wzWFJsWFdNLVd3?oc=5",
              "origin": "google"
            },
            {
              "name": "중앙이코노미뉴스",
              "url": "https://news.google.com/rss/articles/CBMickFVX3lxTE1YdF8tZVV5akhHbW02R2haQUFxbjVUVnRFeDg0c25tU3l2ZC1zdnNRbXVSMnpWQUVraHBsTVJVTGNXNGo5cFJTbHZNNHU5VjI5cFQ1ZlkzNTFjclNoWGNpN2FIRjRKcmNJakNmQnZpZ0ZXUQ?oc=5",
              "origin": "google"
            }
          ],
          "source_count": 4,
          "published": "2026-07-24T11:23:00+09:00",
          "ts": 1784859780.0,
          "group": "central",
          "group_label": "중앙부처(콘텐츠)"
        },
        {
          "title": "한국저작권위원회 '저작권 문화가 있는 날' 2회차 성료",
          "url": "https://www.consumuch.com/news/articleView.html?idxno=78619",
          "snippet": "캠페인에는 사전 신청자와 현장 참여자 등 약 300명이 참여했으며, 영화 관람과 연계해 시민들이 자연스럽게 저작권을 이해하고 올바른 콘텐츠 이용 문화를 체험할 수 있는 기회가 됐다. 영화관 로비에서는 저작권 퀴즈와...",
          "source": "consumuch.com",
          "sources": [
            {
              "name": "consumuch.com",
              "url": "https://www.consumuch.com/news/articleView.html?idxno=78619",
              "origin": "naver"
            },
            {
              "name": "동아일보",
              "url": "https://www.donga.com/news/Culture/article/all/20260723/134350760/1",
              "origin": "naver"
            },
            {
              "name": "koreastocknews.com",
              "url": "http://www.koreastocknews.com/news/articleView.html?idxno=119996",
              "origin": "naver"
            }
          ],
          "source_count": 3,
          "published": "2026-07-23T15:54:00+09:00",
          "ts": 1784789640.0,
          "group": "central",
          "group_label": "중앙부처(콘텐츠)"
        },
        {
          "title": "저작권위원회 공식 유튜브, 소셜아이어워드 3년 연속 수상",
          "url": "https://www.etnews.com/20260724000092",
          "snippet": "강석원 위원장은 “앞으로도 변화하는 디지털 환경과 국민의 정보 수요를 반영한 콘텐츠를 지속 발굴해 신뢰받는 저작권 정보 제공 기관으로서 역할을 다하겠다”고 밝혔다.",
          "source": "전자신문",
          "sources": [
            {
              "name": "전자신문",
              "url": "https://www.etnews.com/20260724000092",
              "origin": "naver"
            },
            {
              "name": "dandinews.com",
              "url": "http://www.dandinews.com/news/articleView.html?idxno=17207",
              "origin": "naver"
            }
          ],
          "source_count": 2,
          "published": "2026-07-24T10:40:00+09:00",
          "ts": 1784857200.0,
          "group": "central",
          "group_label": "중앙부처(콘텐츠)"
        },
        {
          "title": "넵튠, 웹툰 IP 수익 지원 모델 만든다…콘진원 과제 수행 선정",
          "url": "https://www.mk.co.kr/article/12106433",
          "snippet": "넵튠(대표 강율빈)이 한국콘텐츠진흥원(이하 콘진원)에서 추진하는 ‘K-Culture 글로벌 스타트업 육성 기술 개발’ 과제 수행 기업으로 선정됐다. 이번 과제는 슈퍼플래닛, 콘텐츠퍼스트, 고려대학교 인공지능학과...",
          "source": "매일경제",
          "sources": [
            {
              "name": "매일경제",
              "url": "https://www.mk.co.kr/article/12106433",
              "origin": "naver"
            },
            {
              "name": "v.daum.net",
              "url": "https://news.google.com/rss/articles/CBMiT0FVX3lxTE1ZdV9YUTRxeFN5b3ZkdlN2VVJoZF9SUmZ4Y2Z0QUVCSVFSenJKc2haUG9RdHNFcVlNZjY3Qlo1ZkVUUE9ldVBaWFB2SDhLZFk?oc=5",
              "origin": "google"
            }
          ],
          "source_count": 2,
          "published": "2026-07-24T10:37:00+09:00",
          "ts": 1784857020.0,
          "group": "central",
          "group_label": "중앙부처(콘텐츠)"
        },
        {
          "title": "몽규, 문체부·콘진원 ‘혁신 프리미어 1000’ AI 분야 기업 선정",
          "url": "https://www.sentv.co.kr/article/view/sentv202607240049",
          "snippet": "디지털 마케팅 솔루션 회사 몽규는 문화체육관광부와 한국콘텐츠진흥원이 주관하는 ‘혁신 프리미어 1000’ 프로그램의 인공지능(AI) 분야 기업으로 최종 선정됐다고 24일 밝혔다. ‘혁신 프리미어 1000’은 대한민국...",
          "source": "sentv.co.kr",
          "sources": [
            {
              "name": "sentv.co.kr",
              "url": "https://www.sentv.co.kr/article/view/sentv202607240049",
              "origin": "naver"
            },
            {
              "name": "서울경제TV",
              "url": "https://news.google.com/rss/articles/CBMiZEFVX3lxTE82S1VKS0RIVU1CWHlKZmlSdGF6eVRpaWxjRm5jRjJqd0VCaUlNUG9nZ3FyMjZIOEdXbXdMZk5SM3k4WDU1dHBydWlydWRGMDcyWWtyR3V1RWlwaktfQXVTMGpvR3Q?oc=5",
              "origin": "google"
            }
          ],
          "source_count": 2,
          "published": "2026-07-24T10:06:00+09:00",
          "ts": 1784855160.0,
          "group": "central",
          "group_label": "중앙부처(콘텐츠)"
        },
        {
          "title": "문체부·콘진원, K-콘텐츠 중국 진출길 넓힌다",
          "url": "http://www.fnnews.com/news/202607240920219045",
          "snippet": "문화체육관광부와 한국콘텐츠진흥원이 국내 콘텐츠 기업의 중국 시장 진출을 돕기 위해 현지 지원을 확대하고 있다. 베이징과 청두에서 '코리아콘텐츠위크'를 열어 중국 기업과의 상담과 계약·법률 자문...",
          "source": "파이낸셜뉴스",
          "sources": [
            {
              "name": "파이낸셜뉴스",
              "url": "http://www.fnnews.com/news/202607240920219045",
              "origin": "naver"
            },
            {
              "name": "newswhoplus.com",
              "url": "https://www.newswhoplus.com/news/articleView.html?idxno=65256",
              "origin": "naver"
            }
          ],
          "source_count": 2,
          "published": "2026-07-24T09:30:00+09:00",
          "ts": 1784853000.0,
          "group": "central",
          "group_label": "중앙부처(콘텐츠)"
        },
        {
          "title": "문화체육관광부, 영상·방송업계와 손잡고 '인공지능 문화강국' 도약 준비",
          "url": "https://news.google.com/rss/articles/CBMiZ0FVX3lxTE11RVRxU3NqaGhGTHpUVGlXM2FvaGtLaU4wN0JWMHlRREx0Z0xGTW5wcGRsa0hhcGlRS0lncEFLT002VWgtbmYtOURxSVJLa0xvWS1RaVd4YkZ3anFpVlpnR3puSFVXUUE?oc=5",
          "snippet": "",
          "source": "K-Classic News",
          "sources": [
            {
              "name": "K-Classic News",
              "url": "https://news.google.com/rss/articles/CBMiZ0FVX3lxTE11RVRxU3NqaGhGTHpUVGlXM2FvaGtLaU4wN0JWMHlRREx0Z0xGTW5wcGRsa0hhcGlRS0lncEFLT002VWgtbmYtOURxSVJLa0xvWS1RaVd4YkZ3anFpVlpnR3puSFVXUUE?oc=5",
              "origin": "google"
            },
            {
              "name": "fnewstv.com",
              "url": "https://news.google.com/rss/articles/CBMickFVX3lxTE5VZnpBZTRoZUU3ZWRPOWZDSEdZUnJJc2d1aXRrX3dEbXdZQ2ptaXozOW9sSmNJMG5DNWttbzhsRWFVU3NHeWIyb3M4S0hQOFd5T013b1l4MlhlRHY0cVc4VkxhclRLc1hjUV9DeG81Y0otUQ?oc=5",
              "origin": "google"
            }
          ],
          "source_count": 2,
          "published": "2026-07-23T19:10:03+09:00",
          "ts": 1784801403.0,
          "group": "central",
          "group_label": "중앙부처(콘텐츠)"
        },
        {
          "title": "콘진원, 상하이 라이선싱 엑스포 첫 참가… 국내 라이선싱 페어도 흥행",
          "url": "https://www.s-journal.co.kr/news/articleView.html?idxno=42610",
          "snippet": "한국콘텐츠진흥원(이하 콘진원)이 중국 최대 라이선싱 전시회에서 한국공동관을 처음 운영하며 2500만달러 규모 수출 상담 성과를 거뒀다. 국내에서는 '캐릭터 라이선싱 페어 2026'을 통해 1208건의 비즈니스 상담을...",
          "source": "s-journal.co.kr",
          "sources": [
            {
              "name": "s-journal.co.kr",
              "url": "https://www.s-journal.co.kr/news/articleView.html?idxno=42610",
              "origin": "naver"
            }
          ],
          "source_count": 1,
          "published": "2026-07-24T14:14:00+09:00",
          "ts": 1784870040.0,
          "group": "central",
          "group_label": "중앙부처(콘텐츠)"
        },
        {
          "title": "넵튠, 콘진원의 'K-Culture 글로벌 스타트업 육성 기술 개발' 기업으로 ...",
          "url": "https://gamefocus.co.kr/detail.php?number=177687",
          "snippet": "넵튠(대표 강율빈)이 한국콘텐츠진흥원(이하 콘진원)의 ‘K-Culture 글로벌 스타트업 육성 기술 개발’ 과제 수행 기업으로 선정됐다고 밝혔다. 이번 과제는 슈퍼플래닛, 콘텐츠퍼스트, 고려대학교 인공지능학과...",
          "source": "gamefocus.co.kr",
          "sources": [
            {
              "name": "gamefocus.co.kr",
              "url": "https://gamefocus.co.kr/detail.php?number=177687",
              "origin": "naver"
            }
          ],
          "source_count": 1,
          "published": "2026-07-24T10:32:00+09:00",
          "ts": 1784856720.0,
          "group": "central",
          "group_label": "중앙부처(콘텐츠)"
        },
        {
          "title": "AI가 바꾸는 영상 제작 현장…문체부, K-콘텐츠 경쟁력 강화 전략 모색",
          "url": "https://news.google.com/rss/articles/CBMiTEFVX3lxTE0xR3VHcElBU2JtbnQ5cEd4cUtNeEdWNHdKNVU2S3NRSFZTaEI2QkZHcWJ4SkJOSWdvRk4tYTdEbmRNcVBoS24tVk8xbk0?oc=5",
          "snippet": "",
          "source": "한국AI부동산신문",
          "sources": [
            {
              "name": "한국AI부동산신문",
              "url": "https://news.google.com/rss/articles/CBMiTEFVX3lxTE0xR3VHcElBU2JtbnQ5cEd4cUtNeEdWNHdKNVU2S3NRSFZTaEI2QkZHcWJ4SkJOSWdvRk4tYTdEbmRNcVBoS24tVk8xbk0?oc=5",
              "origin": "google"
            }
          ],
          "source_count": 1,
          "published": "2026-07-24T09:42:22+09:00",
          "ts": 1784853742.0,
          "group": "central",
          "group_label": "중앙부처(콘텐츠)"
        },
        {
          "title": "콘진원, 인천공항 'K-컬처 뮤지엄' 기획전 3만 명 돌파",
          "url": "https://news.google.com/rss/articles/CBMiaEFVX3lxTE5odnlPSnNSSXZ3X08yeFpTYmkwUjlUYnpGN3hQdWM1Mi1uRUF5cld1ems1TkNQTklqb1lxWUN1dmI1bjFaSVREQkliT0JTYzdSUWIzLVlDYXhJdkFJQ2hlNDRQMHYzTHBw?oc=5",
          "snippet": "",
          "source": "뉴스테이지",
          "sources": [
            {
              "name": "뉴스테이지",
              "url": "https://news.google.com/rss/articles/CBMiaEFVX3lxTE5odnlPSnNSSXZ3X08yeFpTYmkwUjlUYnpGN3hQdWM1Mi1uRUF5cld1ems1TkNQTklqb1lxWUN1dmI1bjFaSVREQkliT0JTYzdSUWIzLVlDYXhJdkFJQ2hlNDRQMHYzTHBw?oc=5",
              "origin": "google"
            }
          ],
          "source_count": 1,
          "published": "2026-07-24T06:27:36+09:00",
          "ts": 1784842056.0,
          "group": "central",
          "group_label": "중앙부처(콘텐츠)"
        },
        {
          "title": "문체부, 영상·방송업계와 간담회 개최…'AI 문화강국 전략' 수립 박차",
          "url": "https://zdnet.co.kr/view/?no=20260724012606",
          "snippet": "참석해 AI 도입에 따른 창·제작 환경 변화와 현장 애로사항을 논의했다. 문체부는 이번 간담회에서 수렴된 의견과 한국콘텐츠진흥원의 조사 결과 등을 종합해 향후 발표할 AI 문화 정책 전략에 적극 반영할 방침이다.",
          "source": "지디넷코리아",
          "sources": [
            {
              "name": "지디넷코리아",
              "url": "https://zdnet.co.kr/view/?no=20260724012606",
              "origin": "naver"
            }
          ],
          "source_count": 1,
          "published": "2026-07-24T06:21:00+09:00",
          "ts": 1784841660.0,
          "group": "central",
          "group_label": "중앙부처(콘텐츠)"
        },
        {
          "title": "K-애니메이션, 중국 시장 공략 본격화…한국콘텐츠진흥원 공동관 성과",
          "url": "https://news.google.com/rss/articles/CBMiVEFVX3lxTE5MaDBPMUZuNkxzZkxVOEI0SWpwSENlR2FjdUVfRXdTaUFmOGFYR3d4dVVKcC1sMEV0VklDVU9rbXpMWUg0WDU0TjNtNnMyaTM1OE5lRQ?oc=5",
          "snippet": "",
          "source": "시사의창",
          "sources": [
            {
              "name": "시사의창",
              "url": "https://news.google.com/rss/articles/CBMiVEFVX3lxTE5MaDBPMUZuNkxzZkxVOEI0SWpwSENlR2FjdUVfRXdTaUFmOGFYR3d4dVVKcC1sMEV0VklDVU9rbXpMWUg0WDU0TjNtNnMyaTM1OE5lRQ?oc=5",
              "origin": "google"
            }
          ],
          "source_count": 1,
          "published": "2026-07-23T22:34:21+09:00",
          "ts": 1784813661.0,
          "group": "central",
          "group_label": "중앙부처(콘텐츠)"
        },
        {
          "title": "사진=한국콘텐츠진흥원, PH E&M",
          "url": "https://news.google.com/rss/articles/CBMipARBVV95cUxNN1pZT054bFlIcDRPeXp0cVc3NEpOWm82R2hURFl3elA3TXBNSHQ0U09jV3hEaWxfZC1NMHhBcVN3WEhtU0Q4VllyWC1MbVNENTBNRnNHNG5UUzA4Yi16d3NLQkdBUFZaV2hpa2NXRl9vWWNqbE54Q0o1dVg3RGVkQmhNd1J5enM4dnV5UG5DOUdSSG8yZXZQeDZ3QTlCUTdsbHowZm1yNVd4UWdLX3JDZXp3VmU1WHl6M2w0MGstQ2NRS2NXaG9NVlE3R0w5UlNOQW9Obm9pTHJEWExlNVdxWDlFX21TTmtfRnNCQWtIakpYZV96QWt6WWhQYm9QNW9aeGk5SFplSDRpRkZTTThyNXEwbzd1X2JBRUNJZFVLVE9rMkNabk56di1lMWVvNThzV2UtZk1Od1FQYV82NGp0RW9jVHdUemFHaWE1MGNobmhMY0FhbnprQ2NONS1Nblhta2JrZ3hDUmZyZ203cnFMQjJ6SkhrZi1NdnJIQnBXb0RVN0xxOEhaSDlSaVJWNDc2NWFvZGZJQXg1TzRSS1UtOUNmbTZzSmM5azVKU1p2WGFtdmZYZkRPXzkwMXo1SEMxLW9EaUdrVmZUamlBVHctMGZqOUllbkEteW1NN0tFTU52U0J0NEViNG5SeDZzclA3Vk9QeFFrbGRIbTY2ZGYzR2RrTFRjMHk0ZHlydXdaMF91bVJuMS1zU3oxLXNhd3U2LWFQWg?oc=5",
          "snippet": "",
          "source": "전자신문",
          "sources": [
            {
              "name": "전자신문",
              "url": "https://news.google.com/rss/articles/CBMipARBVV95cUxNN1pZT054bFlIcDRPeXp0cVc3NEpOWm82R2hURFl3elA3TXBNSHQ0U09jV3hEaWxfZC1NMHhBcVN3WEhtU0Q4VllyWC1MbVNENTBNRnNHNG5UUzA4Yi16d3NLQkdBUFZaV2hpa2NXRl9vWWNqbE54Q0o1dVg3RGVkQmhNd1J5enM4dnV5UG5DOUdSSG8yZXZQeDZ3QTlCUTdsbHowZm1yNVd4UWdLX3JDZXp3VmU1WHl6M2w0MGstQ2NRS2NXaG9NVlE3R0w5UlNOQW9Obm9pTHJEWExlNVdxWDlFX21TTmtfRnNCQWtIakpYZV96QWt6WWhQYm9QNW9aeGk5SFplSDRpRkZTTThyNXEwbzd1X2JBRUNJZFVLVE9rMkNabk56di1lMWVvNThzV2UtZk1Od1FQYV82NGp0RW9jVHdUemFHaWE1MGNobmhMY0FhbnprQ2NONS1Nblhta2JrZ3hDUmZyZ203cnFMQjJ6SkhrZi1NdnJIQnBXb0RVN0xxOEhaSDlSaVJWNDc2NWFvZGZJQXg1TzRSS1UtOUNmbTZzSmM5azVKU1p2WGFtdmZYZkRPXzkwMXo1SEMxLW9EaUdrVmZUamlBVHctMGZqOUllbkEteW1NN0tFTU52U0J0NEViNG5SeDZzclA3Vk9QeFFrbGRIbTY2ZGYzR2RrTFRjMHk0ZHlydXdaMF91bVJuMS1zU3oxLXNhd3U2LWFQWg?oc=5",
              "origin": "google"
            }
          ],
          "source_count": 1,
          "published": "2026-07-23T22:09:34+09:00",
          "ts": 1784812174.0,
          "group": "central",
          "group_label": "중앙부처(콘텐츠)"
        },
        {
          "title": "콘진원, '2026 라이선싱 엑스포 차이나' 한국 공동관 성료",
          "url": "http://www.worktoday.co.kr/news/articleView.html?idxno=87058",
          "snippet": "'2026 라이선싱 엑스포 차이나' 한국공동관 전경 문화체육관광부(장관 최휘영)와 한국콘텐츠진흥원(원장 김윤지, 이하 콘진원)은 지난 15일부터 17일까지 중국 상하이에서 열린 '2026 라이선싱 엑스포 차이나'에서...",
          "source": "worktoday.co.kr",
          "sources": [
            {
              "name": "worktoday.co.kr",
              "url": "http://www.worktoday.co.kr/news/articleView.html?idxno=87058",
              "origin": "naver"
            }
          ],
          "source_count": 1,
          "published": "2026-07-23T17:10:00+09:00",
          "ts": 1784794200.0,
          "group": "central",
          "group_label": "중앙부처(콘텐츠)"
        }
      ]
    }
  ]
}